{
"meta":{"test_sets":[],"test_metrics":[],"learn_metrics":[{"best_value":"Min","name":"RMSE"}],"launch_mode":"Train","parameters":"","iteration_count":1000,"learn_sets":["learn"],"name":"experiment"},
"iterations":[
{"learn":[706.1231392],"iteration":0,"passed_time":0.01092772261,"remaining_time":10.91679489},
{"learn":[697.6752032],"iteration":1,"passed_time":0.02371405054,"remaining_time":11.83331122},
{"learn":[690.0114878],"iteration":2,"passed_time":0.03410170764,"remaining_time":11.33313417},
{"learn":[683.0479129],"iteration":3,"passed_time":0.04666933445,"remaining_time":11.62066428},
{"learn":[676.82838],"iteration":4,"passed_time":0.05787350627,"remaining_time":11.51682775},
{"learn":[670.9543937],"iteration":5,"passed_time":0.06847803122,"remaining_time":11.34452717},
{"learn":[665.7495696],"iteration":6,"passed_time":0.07967441163,"remaining_time":11.30238439},
{"learn":[661.2763254],"iteration":7,"passed_time":0.09021398038,"remaining_time":11.18653357},
{"learn":[657.515342],"iteration":8,"passed_time":0.09635452769,"remaining_time":10.6097041},
{"learn":[654.1617571],"iteration":9,"passed_time":0.1051460708,"remaining_time":10.40946101},
{"learn":[650.5111826],"iteration":10,"passed_time":0.1165290284,"remaining_time":10.47701901},
{"learn":[647.3502616],"iteration":11,"passed_time":0.1270024743,"remaining_time":10.45653705},
{"learn":[644.33603],"iteration":12,"passed_time":0.1386005082,"remaining_time":10.52297704},
{"learn":[641.3839031],"iteration":13,"passed_time":0.1499517585,"remaining_time":10.56088813},
{"learn":[638.8603833],"iteration":14,"passed_time":0.1609941023,"remaining_time":10.57194605},
{"learn":[636.6236284],"iteration":15,"passed_time":0.1712171398,"remaining_time":10.5298541},
{"learn":[634.6185193],"iteration":16,"passed_time":0.1836891864,"remaining_time":10.62155708},
{"learn":[632.7475525],"iteration":17,"passed_time":0.1948944832,"remaining_time":10.63257681},
{"learn":[631.034558],"iteration":18,"passed_time":0.2077847661,"remaining_time":10.72825555},
{"learn":[629.4032474],"iteration":19,"passed_time":0.2189249817,"remaining_time":10.7273241},
{"learn":[628.3007882],"iteration":20,"passed_time":0.227183459,"remaining_time":10.5910765},
{"learn":[626.9158375],"iteration":21,"passed_time":0.2385049603,"remaining_time":10.6026296},
{"learn":[625.8236978],"iteration":22,"passed_time":0.2479618982,"remaining_time":10.5329902},
{"learn":[624.8889863],"iteration":23,"passed_time":0.2576935352,"remaining_time":10.4795371},
{"learn":[623.8879203],"iteration":24,"passed_time":0.2669985198,"remaining_time":10.41294227},
{"learn":[622.8240148],"iteration":25,"passed_time":0.2790801209,"remaining_time":10.45477068},
{"learn":[621.8817354],"iteration":26,"passed_time":0.2899846777,"remaining_time":10.45018857},
{"learn":[621.0608738],"iteration":27,"passed_time":0.298810428,"remaining_time":10.37299057},
{"learn":[620.2102716],"iteration":28,"passed_time":0.3080180824,"remaining_time":10.3132951},
{"learn":[619.5711569],"iteration":29,"passed_time":0.3164630536,"remaining_time":10.2323054},
{"learn":[618.7716116],"iteration":30,"passed_time":0.3265428042,"remaining_time":10.20709604},
{"learn":[618.0431274],"iteration":31,"passed_time":0.336657637,"remaining_time":10.18389352},
{"learn":[617.346578],"iteration":32,"passed_time":0.3463084017,"remaining_time":10.14788559},
{"learn":[616.5261684],"iteration":33,"passed_time":0.3586820766,"remaining_time":10.19079077},
{"learn":[615.7644096],"iteration":34,"passed_time":0.3696445898,"remaining_time":10.1916294},
{"learn":[615.1741484],"iteration":35,"passed_time":0.380331112,"remaining_time":10.184422},
{"learn":[614.6132684],"iteration":36,"passed_time":0.3885605487,"remaining_time":10.1130759},
{"learn":[614.0091007],"iteration":37,"passed_time":0.3984836378,"remaining_time":10.08792788},
{"learn":[613.6174168],"iteration":38,"passed_time":0.4075889206,"remaining_time":10.04340904},
{"learn":[612.924263],"iteration":39,"passed_time":0.4178410405,"remaining_time":10.02818497},
{"learn":[612.1675373],"iteration":40,"passed_time":0.42997339,"remaining_time":10.05718246},
{"learn":[611.6086556],"iteration":41,"passed_time":0.4391824193,"remaining_time":10.01754185},
{"learn":[611.0767494],"iteration":42,"passed_time":0.4474960199,"remaining_time":9.959388164},
{"learn":[610.6887712],"iteration":43,"passed_time":0.455964282,"remaining_time":9.906860309},
{"learn":[610.4027524],"iteration":44,"passed_time":0.4616579691,"remaining_time":9.79740801},
{"learn":[609.9956271],"iteration":45,"passed_time":0.4701309811,"remaining_time":9.750107737},
{"learn":[609.6147997],"iteration":46,"passed_time":0.4800348625,"remaining_time":9.733472849},
{"learn":[609.2987247],"iteration":47,"passed_time":0.4874107856,"remaining_time":9.666980582},
{"learn":[608.9796385],"iteration":48,"passed_time":0.4954193963,"remaining_time":9.615180528},
{"learn":[608.6142242],"iteration":49,"passed_time":0.5028514843,"remaining_time":9.554178201},
{"learn":[608.2048223],"iteration":50,"passed_time":0.512352129,"remaining_time":9.533768048},
{"learn":[607.8772654],"iteration":51,"passed_time":0.5213220829,"remaining_time":9.504102588},
{"learn":[607.362312],"iteration":52,"passed_time":0.5311936321,"remaining_time":9.491327727},
{"learn":[607.1435668],"iteration":53,"passed_time":0.5371371442,"remaining_time":9.409847007},
{"learn":[606.8779257],"iteration":54,"passed_time":0.5447691423,"remaining_time":9.360124353},
{"learn":[606.640579],"iteration":55,"passed_time":0.551623416,"remaining_time":9.298794727},
{"learn":[606.4123072],"iteration":56,"passed_time":0.5579694149,"remaining_time":9.230967688},
{"learn":[606.2501071],"iteration":57,"passed_time":0.5641854597,"remaining_time":9.163150052},
{"learn":[605.9742244],"iteration":58,"passed_time":0.5734080302,"remaining_time":9.145372143},
{"learn":[605.7840134],"iteration":59,"passed_time":0.5802850532,"remaining_time":9.0911325},
{"learn":[605.4931103],"iteration":60,"passed_time":0.5889642667,"remaining_time":9.066187647},
{"learn":[605.0810281],"iteration":61,"passed_time":0.5985430755,"remaining_time":9.055377497},
{"learn":[604.9640075],"iteration":62,"passed_time":0.6043902158,"remaining_time":8.989105274},
{"learn":[604.5843373],"iteration":63,"passed_time":0.6126828171,"remaining_time":8.9604862},
{"learn":[604.2682967],"iteration":64,"passed_time":0.6222711673,"remaining_time":8.951131406},
{"learn":[604.0455204],"iteration":65,"passed_time":0.6288411171,"remaining_time":8.899054596},
{"learn":[603.694492],"iteration":66,"passed_time":0.6389092014,"remaining_time":8.897049028},
{"learn":[603.463156],"iteration":67,"passed_time":0.6462492508,"remaining_time":8.857416201},
{"learn":[603.2948242],"iteration":68,"passed_time":0.6518419411,"remaining_time":8.795142713},
{"learn":[603.0106315],"iteration":69,"passed_time":0.6615452042,"remaining_time":8.78910057},
{"learn":[602.7700466],"iteration":70,"passed_time":0.6685520979,"remaining_time":8.747674633},
{"learn":[602.5065877],"iteration":71,"passed_time":0.6758195246,"remaining_time":8.710562762},
{"learn":[602.3194479],"iteration":72,"passed_time":0.6826183419,"remaining_time":8.668317848},
{"learn":[602.1495765],"iteration":73,"passed_time":0.6889866733,"remaining_time":8.621644047},
{"learn":[601.9042324],"iteration":74,"passed_time":0.6967342509,"remaining_time":8.593055761},
{"learn":[601.6353627],"iteration":75,"passed_time":0.7031953293,"remaining_time":8.549374793},
{"learn":[601.5352643],"iteration":76,"passed_time":0.7085750684,"remaining_time":8.493698547},
{"learn":[601.4009588],"iteration":77,"passed_time":0.7150828952,"remaining_time":8.452646531},
{"learn":[601.0784989],"iteration":78,"passed_time":0.7245720403,"remaining_time":8.447225939},
{"learn":[600.8035962],"iteration":79,"passed_time":0.7316690977,"remaining_time":8.414194624},
{"learn":[600.6081255],"iteration":80,"passed_time":0.7391278515,"remaining_time":8.385907352},
{"learn":[600.4868075],"iteration":81,"passed_time":0.7450467811,"remaining_time":8.340889574},
{"learn":[600.250327],"iteration":82,"passed_time":0.7540957741,"remaining_time":8.33139548},
{"learn":[600.0582389],"iteration":83,"passed_time":0.7604540225,"remaining_time":8.292570055},
{"learn":[599.8733047],"iteration":84,"passed_time":0.7670398885,"remaining_time":8.256958799},
{"learn":[599.6234173],"iteration":85,"passed_time":0.7745437658,"remaining_time":8.231779092},
{"learn":[599.4358695],"iteration":86,"passed_time":0.7831646895,"remaining_time":8.218728294},
{"learn":[599.2723299],"iteration":87,"passed_time":0.7893658182,"remaining_time":8.180700297},
{"learn":[599.0799459],"iteration":88,"passed_time":0.7956258199,"remaining_time":8.143990134},
{"learn":[598.8891528],"iteration":89,"passed_time":0.8037448018,"remaining_time":8.126752996},
{"learn":[598.7038612],"iteration":90,"passed_time":0.8115301699,"remaining_time":8.106383785},
{"learn":[598.5221158],"iteration":91,"passed_time":0.8185140227,"remaining_time":8.078377528},
{"learn":[598.4543739],"iteration":92,"passed_time":0.8243126646,"remaining_time":8.039264374},
{"learn":[598.1484637],"iteration":93,"passed_time":0.8360717764,"remaining_time":8.058308824},
{"learn":[597.9997796],"iteration":94,"passed_time":0.8436395266,"remaining_time":8.036776543},
{"learn":[597.8431884],"iteration":95,"passed_time":0.8504707594,"remaining_time":8.008599651},
{"learn":[597.6952868],"iteration":96,"passed_time":0.8571365811,"remaining_time":7.979323018},
{"learn":[597.4335141],"iteration":97,"passed_time":0.8643030945,"remaining_time":7.955116237},
{"learn":[597.3103052],"iteration":98,"passed_time":0.8696912916,"remaining_time":7.91506923},
{"learn":[597.0610725],"iteration":99,"passed_time":0.878567832,"remaining_time":7.907110488},
{"learn":[596.8621912],"iteration":100,"passed_time":0.8853176925,"remaining_time":7.880204015},
{"learn":[596.7385206],"iteration":101,"passed_time":0.8932363894,"remaining_time":7.863983115},
{"learn":[596.6167827],"iteration":102,"passed_time":0.8997174671,"remaining_time":7.835403573},
{"learn":[596.4229756],"iteration":103,"passed_time":0.9082275196,"remaining_time":7.824729399},
{"learn":[596.3616178],"iteration":104,"passed_time":0.9136305912,"remaining_time":7.787613135},
{"learn":[596.2191874],"iteration":105,"passed_time":0.9218205709,"remaining_time":7.774599909},
{"learn":[596.0264837],"iteration":106,"passed_time":0.9288243397,"remaining_time":7.751776966},
{"learn":[595.9231319],"iteration":107,"passed_time":0.9351058823,"remaining_time":7.723281917},
{"learn":[595.8460571],"iteration":108,"passed_time":0.9416868734,"remaining_time":7.69764224},
{"learn":[595.7174347],"iteration":109,"passed_time":0.9486707262,"remaining_time":7.675608603},
{"learn":[595.5418382],"iteration":110,"passed_time":0.9568638307,"remaining_time":7.663531041},
{"learn":[595.3860391],"iteration":111,"passed_time":0.9644239562,"remaining_time":7.646504224},
{"learn":[595.2860972],"iteration":112,"passed_time":0.9706647085,"remaining_time":7.619288464},
{"learn":[595.1801904],"iteration":113,"passed_time":0.9776786437,"remaining_time":7.598449809},
{"learn":[595.1093311],"iteration":114,"passed_time":0.9842155112,"remaining_time":7.574180238},
{"learn":[594.8242037],"iteration":115,"passed_time":0.9925248203,"remaining_time":7.56372363},
{"learn":[594.5175305],"iteration":116,"passed_time":1.000402977,"remaining_time":7.550049817},
{"learn":[594.2339455],"iteration":117,"passed_time":1.008401296,"remaining_time":7.5373724},
{"learn":[594.1147865],"iteration":118,"passed_time":1.014800043,"remaining_time":7.512931413},
{"learn":[594.0007849],"iteration":119,"passed_time":1.021550654,"remaining_time":7.491371461},
{"learn":[593.8473339],"iteration":120,"passed_time":1.027873487,"remaining_time":7.466948718},
{"learn":[593.7125653],"iteration":121,"passed_time":1.034253609,"remaining_time":7.443234993},
{"learn":[593.5083817],"iteration":122,"passed_time":1.04196098,"remaining_time":7.4292665},
{"learn":[593.3986632],"iteration":123,"passed_time":1.049094286,"remaining_time":7.411343506},
{"learn":[593.210181],"iteration":124,"passed_time":1.057413512,"remaining_time":7.401894581},
{"learn":[593.1141519],"iteration":125,"passed_time":1.064612232,"remaining_time":7.384691199},
{"learn":[593.0213079],"iteration":126,"passed_time":1.071213014,"remaining_time":7.363535131},
{"learn":[592.9048712],"iteration":127,"passed_time":1.077440434,"remaining_time":7.340062956},
{"learn":[592.8064084],"iteration":128,"passed_time":1.084364164,"remaining_time":7.321559586},
{"learn":[592.6357759],"iteration":129,"passed_time":1.091921664,"remaining_time":7.307475753},
{"learn":[592.5093199],"iteration":130,"passed_time":1.098456823,"remaining_time":7.286709768},
{"learn":[592.4291804],"iteration":131,"passed_time":1.105805081,"remaining_time":7.271506138},
{"learn":[592.1525459],"iteration":132,"passed_time":1.115240853,"remaining_time":7.270028717},
{"learn":[591.9006107],"iteration":133,"passed_time":1.123938024,"remaining_time":7.26365917},
{"learn":[591.7714531],"iteration":134,"passed_time":1.132462201,"remaining_time":7.256146695},
{"learn":[591.4821216],"iteration":135,"passed_time":1.141909431,"remaining_time":7.254483442},
{"learn":[591.261866],"iteration":136,"passed_time":1.15000908,"remaining_time":7.244217782},
{"learn":[591.0468402],"iteration":137,"passed_time":1.159319731,"remaining_time":7.241547885},
{"learn":[590.9144142],"iteration":138,"passed_time":1.166545409,"remaining_time":7.225867607},
{"learn":[590.7896271],"iteration":139,"passed_time":1.173345518,"remaining_time":7.207693897},
{"learn":[590.6583863],"iteration":140,"passed_time":1.180110045,"remaining_time":7.189464741},
{"learn":[590.4285156],"iteration":141,"passed_time":1.188521892,"remaining_time":7.181350587},
{"learn":[590.3206603],"iteration":142,"passed_time":1.195956105,"remaining_time":7.167373301},
{"learn":[590.2935958],"iteration":143,"passed_time":1.20211511,"remaining_time":7.145906487},
{"learn":[590.2103154],"iteration":144,"passed_time":1.208553523,"remaining_time":7.126298357},
{"learn":[589.9951352],"iteration":145,"passed_time":1.218163872,"remaining_time":7.125424292},
{"learn":[589.9110515],"iteration":146,"passed_time":1.224736905,"remaining_time":7.106806666},
{"learn":[589.8618281],"iteration":147,"passed_time":1.231480349,"remaining_time":7.08933282},
{"learn":[589.6496641],"iteration":148,"passed_time":1.239490501,"remaining_time":7.079237695},
{"learn":[589.5292815],"iteration":149,"passed_time":1.246666598,"remaining_time":7.064444054},
{"learn":[589.386723],"iteration":150,"passed_time":1.253906442,"remaining_time":7.050109731},
{"learn":[589.1361243],"iteration":151,"passed_time":1.2632488,"remaining_time":7.04759857},
{"learn":[588.9755042],"iteration":152,"passed_time":1.271804435,"remaining_time":7.04064285},
{"learn":[588.8837546],"iteration":153,"passed_time":1.278686874,"remaining_time":7.024474646},
{"learn":[588.8396637],"iteration":154,"passed_time":1.284310313,"remaining_time":7.001562677},
{"learn":[588.6151357],"iteration":155,"passed_time":1.292770409,"remaining_time":6.994219393},
{"learn":[588.4484992],"iteration":156,"passed_time":1.301600451,"remaining_time":6.988848282},
{"learn":[588.3582717],"iteration":157,"passed_time":1.307900243,"remaining_time":6.969949397},
{"learn":[588.2697167],"iteration":158,"passed_time":1.313962918,"remaining_time":6.949954805},
{"learn":[588.1367135],"iteration":159,"passed_time":1.322248853,"remaining_time":6.941806477},
{"learn":[588.07601],"iteration":160,"passed_time":1.327912166,"remaining_time":6.919989485},
{"learn":[588.0119244],"iteration":161,"passed_time":1.334483449,"remaining_time":6.903068705},
{"learn":[587.880328],"iteration":162,"passed_time":1.341069648,"remaining_time":6.886351506},
{"learn":[587.8097892],"iteration":163,"passed_time":1.347642265,"remaining_time":6.869688617},
{"learn":[587.720662],"iteration":164,"passed_time":1.354642867,"remaining_time":6.855313902},
{"learn":[587.6392495],"iteration":165,"passed_time":1.360991324,"remaining_time":6.837751591},
{"learn":[587.559258],"iteration":166,"passed_time":1.367358989,"remaining_time":6.820419387},
{"learn":[587.4382732],"iteration":167,"passed_time":1.374086933,"remaining_time":6.805001955},
{"learn":[587.2572537],"iteration":168,"passed_time":1.383459874,"remaining_time":6.802693226},
{"learn":[587.1791857],"iteration":169,"passed_time":1.390647678,"remaining_time":6.789632782},
{"learn":[586.9089451],"iteration":170,"passed_time":1.400760344,"remaining_time":6.790820617},
{"learn":[586.8525992],"iteration":171,"passed_time":1.406639109,"remaining_time":6.771495244},
{"learn":[586.7261558],"iteration":172,"passed_time":1.413348887,"remaining_time":6.75629786},
{"learn":[586.6411126],"iteration":173,"passed_time":1.419191903,"remaining_time":6.7370834},
{"learn":[586.5579066],"iteration":174,"passed_time":1.424826925,"remaining_time":6.717041218},
{"learn":[586.3622959],"iteration":175,"passed_time":1.433770005,"remaining_time":6.712650477},
{"learn":[586.2706501],"iteration":176,"passed_time":1.440404536,"remaining_time":6.697474198},
{"learn":[586.1626954],"iteration":177,"passed_time":1.448171696,"remaining_time":6.687624349},
{"learn":[585.9140553],"iteration":178,"passed_time":1.456684832,"remaining_time":6.681219256},
{"learn":[585.718686],"iteration":179,"passed_time":1.464847479,"remaining_time":6.673194071},
{"learn":[585.612474],"iteration":180,"passed_time":1.471866331,"remaining_time":6.65999185},
{"learn":[585.5146791],"iteration":181,"passed_time":1.478631566,"remaining_time":6.645717696},
{"learn":[585.4109266],"iteration":182,"passed_time":1.4864266,"remaining_time":6.636123127},
{"learn":[585.317844],"iteration":183,"passed_time":1.493085047,"remaining_time":6.621507599},
{"learn":[585.1769702],"iteration":184,"passed_time":1.500038234,"remaining_time":6.608276544},
{"learn":[585.0495702],"iteration":185,"passed_time":1.508282837,"remaining_time":6.600764673},
{"learn":[584.9943141],"iteration":186,"passed_time":1.514645627,"remaining_time":6.585063607},
{"learn":[584.8185032],"iteration":187,"passed_time":1.522364664,"remaining_time":6.575319717},
{"learn":[584.7429604],"iteration":188,"passed_time":1.529267311,"remaining_time":6.562094122},
{"learn":[584.6397409],"iteration":189,"passed_time":1.535976506,"remaining_time":6.548110368},
{"learn":[584.4906298],"iteration":190,"passed_time":1.544409353,"remaining_time":6.541503488},
{"learn":[584.4002848],"iteration":191,"passed_time":1.550164788,"remaining_time":6.523610148},
{"learn":[584.2436987],"iteration":192,"passed_time":1.558942248,"remaining_time":6.518478726},
{"learn":[584.1402362],"iteration":193,"passed_time":1.565991682,"remaining_time":6.50613039},
{"learn":[584.0452791],"iteration":194,"passed_time":1.57352235,"remaining_time":6.495823034},
{"learn":[583.9060463],"iteration":195,"passed_time":1.580392873,"remaining_time":6.482836072},
{"learn":[583.7929492],"iteration":196,"passed_time":1.588868177,"remaining_time":6.476452517},
{"learn":[583.5771368],"iteration":197,"passed_time":1.598198452,"remaining_time":6.473510902},
{"learn":[583.4040248],"iteration":198,"passed_time":1.606310726,"remaining_time":6.46560247},
{"learn":[583.3665646],"iteration":199,"passed_time":1.612405566,"remaining_time":6.449622266},
{"learn":[583.2314009],"iteration":200,"passed_time":1.620177518,"remaining_time":6.440407149},
{"learn":[583.1641365],"iteration":201,"passed_time":1.62674726,"remaining_time":6.426456996},
{"learn":[583.0804743],"iteration":202,"passed_time":1.633073468,"remaining_time":6.411623417},
{"learn":[582.9711518],"iteration":203,"passed_time":1.640368518,"remaining_time":6.400653631},
{"learn":[582.8220834],"iteration":204,"passed_time":1.64864837,"remaining_time":6.393538801},
{"learn":[582.7765346],"iteration":205,"passed_time":1.654574258,"remaining_time":6.377339615},
{"learn":[582.6231832],"iteration":206,"passed_time":1.662765529,"remaining_time":6.369918186},
{"learn":[582.4790445],"iteration":207,"passed_time":1.66980513,"remaining_time":6.358104149},
{"learn":[582.3686164],"iteration":208,"passed_time":1.677031183,"remaining_time":6.347041463},
{"learn":[582.3089471],"iteration":209,"passed_time":1.684355775,"remaining_time":6.33638601},
{"learn":[582.1183278],"iteration":210,"passed_time":1.693400768,"remaining_time":6.332195288},
{"learn":[582.0508076],"iteration":211,"passed_time":1.699935969,"remaining_time":6.318629921},
{"learn":[582.0167201],"iteration":212,"passed_time":1.705471453,"remaining_time":6.301436776},
{"learn":[581.8842198],"iteration":213,"passed_time":1.71266034,"remaining_time":6.290425362},
{"learn":[581.8153563],"iteration":214,"passed_time":1.71837661,"remaining_time":6.274072739},
{"learn":[581.5367255],"iteration":215,"passed_time":1.727807674,"remaining_time":6.271301927},
{"learn":[581.4278714],"iteration":216,"passed_time":1.735278052,"remaining_time":6.261394999},
{"learn":[581.4008958],"iteration":217,"passed_time":1.741622884,"remaining_time":6.247472915},
{"learn":[581.3408647],"iteration":218,"passed_time":1.747739391,"remaining_time":6.232805772},
{"learn":[581.1953386],"iteration":219,"passed_time":1.755900246,"remaining_time":6.22546451},
{"learn":[581.0806927],"iteration":220,"passed_time":1.762791727,"remaining_time":6.213641428},
{"learn":[580.9407216],"iteration":221,"passed_time":1.769971532,"remaining_time":6.202873206},
{"learn":[580.8637739],"iteration":222,"passed_time":1.776696685,"remaining_time":6.190553023},
{"learn":[580.7944595],"iteration":223,"passed_time":1.783686787,"remaining_time":6.179200657},
{"learn":[580.7178985],"iteration":224,"passed_time":1.789896666,"remaining_time":6.165199627},
{"learn":[580.6629999],"iteration":225,"passed_time":1.795836178,"remaining_time":6.150341601},
{"learn":[580.5296139],"iteration":226,"passed_time":1.802097388,"remaining_time":6.136657625},
{"learn":[580.4551713],"iteration":227,"passed_time":1.808964495,"remaining_time":6.125090307},
{"learn":[580.3373496],"iteration":228,"passed_time":1.818248897,"remaining_time":6.121702617},
{"learn":[580.2934211],"iteration":229,"passed_time":1.823675217,"remaining_time":6.105347467},
{"learn":[580.1859604],"iteration":230,"passed_time":1.830222168,"remaining_time":6.09281752},
{"learn":[580.1126195],"iteration":231,"passed_time":1.836273927,"remaining_time":6.078699895},
{"learn":[580.0164361],"iteration":232,"passed_time":1.843498271,"remaining_time":6.068511477},
{"learn":[579.9747884],"iteration":233,"passed_time":1.849692359,"remaining_time":6.054975841},
{"learn":[579.9230876],"iteration":234,"passed_time":1.855884279,"remaining_time":6.041495632},
{"learn":[579.7255558],"iteration":235,"passed_time":1.864352833,"remaining_time":6.035447307},
{"learn":[579.6133115],"iteration":236,"passed_time":1.87170759,"remaining_time":6.025792791},
{"learn":[579.4574256],"iteration":237,"passed_time":1.878959101,"remaining_time":6.015827037},
{"learn":[579.305376],"iteration":238,"passed_time":1.887049917,"remaining_time":6.008556431},
{"learn":[579.0506039],"iteration":239,"passed_time":1.896510938,"remaining_time":6.005617971},
{"learn":[578.902963],"iteration":240,"passed_time":1.904072689,"remaining_time":5.996643861},
{"learn":[578.8463355],"iteration":241,"passed_time":1.909681462,"remaining_time":5.981564248},
{"learn":[578.7632611],"iteration":242,"passed_time":1.915824092,"remaining_time":5.96822567},
{"learn":[578.7049666],"iteration":243,"passed_time":1.923019355,"remaining_time":5.958207509},
{"learn":[578.5307249],"iteration":244,"passed_time":1.931044423,"remaining_time":5.950769549},
{"learn":[578.3108516],"iteration":245,"passed_time":1.940564817,"remaining_time":5.94791005},
{"learn":[578.1008172],"iteration":246,"passed_time":1.950275538,"remaining_time":5.945576844},
{"learn":[578.0364351],"iteration":247,"passed_time":1.956472375,"remaining_time":5.932529139},
{"learn":[577.9341454],"iteration":248,"passed_time":1.964446321,"remaining_time":5.924896332},
{"learn":[577.8748895],"iteration":249,"passed_time":1.971595251,"remaining_time":5.914785754},
{"learn":[577.7897853],"iteration":250,"passed_time":1.979196125,"remaining_time":5.906047402},
{"learn":[577.704537],"iteration":251,"passed_time":1.986206352,"remaining_time":5.895564887},
{"learn":[577.6131574],"iteration":252,"passed_time":1.993741645,"remaining_time":5.886660115},
{"learn":[577.4523839],"iteration":253,"passed_time":2.001154109,"remaining_time":5.877405375},
{"learn":[577.3723367],"iteration":254,"passed_time":2.006863837,"remaining_time":5.863190426},
{"learn":[577.3209211],"iteration":255,"passed_time":2.012380822,"remaining_time":5.848481763},
{"learn":[577.1024202],"iteration":256,"passed_time":2.023038303,"remaining_time":5.848706067},
{"learn":[577.0397645],"iteration":257,"passed_time":2.029618419,"remaining_time":5.83711964},
{"learn":[576.8580865],"iteration":258,"passed_time":2.037748984,"remaining_time":5.830007712},
{"learn":[576.7547883],"iteration":259,"passed_time":2.044655881,"remaining_time":5.8194052},
{"learn":[576.6728871],"iteration":260,"passed_time":2.051039754,"remaining_time":5.807350108},
{"learn":[576.6072639],"iteration":261,"passed_time":2.057318338,"remaining_time":5.795041731},
{"learn":[576.5386636],"iteration":262,"passed_time":2.063698919,"remaining_time":5.783065032},
{"learn":[576.4407441],"iteration":263,"passed_time":2.070599317,"remaining_time":5.772579913},
{"learn":[576.3968678],"iteration":264,"passed_time":2.076214964,"remaining_time":5.758558486},
{"learn":[576.254864],"iteration":265,"passed_time":2.084569355,"remaining_time":5.752157545},
{"learn":[576.1306144],"iteration":266,"passed_time":2.091993069,"remaining_time":5.743186964},
{"learn":[576.0406266],"iteration":267,"passed_time":2.09958761,"remaining_time":5.734694516},
{"learn":[575.8490464],"iteration":268,"passed_time":2.107068571,"remaining_time":5.725900094},
{"learn":[575.6588624],"iteration":269,"passed_time":2.117303941,"remaining_time":5.724562508},
{"learn":[575.6093755],"iteration":270,"passed_time":2.122839009,"remaining_time":5.710515267},
{"learn":[575.4951528],"iteration":271,"passed_time":2.130086936,"remaining_time":5.701115035},
{"learn":[575.4301275],"iteration":272,"passed_time":2.136420769,"remaining_time":5.689296333},
{"learn":[575.365813],"iteration":273,"passed_time":2.144090932,"remaining_time":5.681058456},
{"learn":[575.2654075],"iteration":274,"passed_time":2.151582935,"remaining_time":5.67235501},
{"learn":[575.1259802],"iteration":275,"passed_time":2.159255432,"remaining_time":5.664133813},
{"learn":[575.0541553],"iteration":276,"passed_time":2.166402696,"remaining_time":5.654545664},
{"learn":[574.9620045],"iteration":277,"passed_time":2.17309185,"remaining_time":5.643785308},
{"learn":[574.8984892],"iteration":278,"passed_time":2.179584136,"remaining_time":5.632545383},
{"learn":[574.8454685],"iteration":279,"passed_time":2.186339829,"remaining_time":5.622016704},
{"learn":[574.7874489],"iteration":280,"passed_time":2.1932951,"remaining_time":5.61202554},
{"learn":[574.7055338],"iteration":281,"passed_time":2.200837351,"remaining_time":5.603550418},
{"learn":[574.6294186],"iteration":282,"passed_time":2.207969865,"remaining_time":5.594043793},
{"learn":[574.5286611],"iteration":283,"passed_time":2.214867013,"remaining_time":5.583960497},
{"learn":[574.3907508],"iteration":284,"passed_time":2.222235269,"remaining_time":5.575081465},
{"learn":[574.2576323],"iteration":285,"passed_time":2.230640867,"remaining_time":5.568802724},
{"learn":[574.117883],"iteration":286,"passed_time":2.239123754,"remaining_time":5.562701172},
{"learn":[574.0563259],"iteration":287,"passed_time":2.246857998,"remaining_time":5.554732273},
{"learn":[574.0032407],"iteration":288,"passed_time":2.252932631,"remaining_time":5.542682009},
{"learn":[573.9662015],"iteration":289,"passed_time":2.25906772,"remaining_time":5.53082097},
{"learn":[573.9126177],"iteration":290,"passed_time":2.266098321,"remaining_time":5.521181134},
{"learn":[573.7838672],"iteration":291,"passed_time":2.273926063,"remaining_time":5.513491961},
{"learn":[573.7643154],"iteration":292,"passed_time":2.280543428,"remaining_time":5.502881241},
{"learn":[573.6895162],"iteration":293,"passed_time":2.287248998,"remaining_time":5.492509499},
{"learn":[573.6747033],"iteration":294,"passed_time":2.293062306,"remaining_time":5.480030258},
{"learn":[573.5338955],"iteration":295,"passed_time":2.301207746,"remaining_time":5.473142747},
{"learn":[573.2937403],"iteration":296,"passed_time":2.312007223,"remaining_time":5.472528881},
{"learn":[573.2321044],"iteration":297,"passed_time":2.318911286,"remaining_time":5.462670212},
{"learn":[573.1254615],"iteration":298,"passed_time":2.326523952,"remaining_time":5.454492609},
{"learn":[573.0235762],"iteration":299,"passed_time":2.334130284,"remaining_time":5.446303996},
{"learn":[572.9041499],"iteration":300,"passed_time":2.34177349,"remaining_time":5.438204882},
{"learn":[572.8740592],"iteration":301,"passed_time":2.347967244,"remaining_time":5.426758729},
{"learn":[572.6466496],"iteration":302,"passed_time":2.358853093,"remaining_time":5.426140613},
{"learn":[572.6049497],"iteration":303,"passed_time":2.36496335,"remaining_time":5.414521353},
{"learn":[572.4944874],"iteration":304,"passed_time":2.37272151,"remaining_time":5.406693277},
{"learn":[572.3699989],"iteration":305,"passed_time":2.380746454,"remaining_time":5.399470715},
{"learn":[572.3180108],"iteration":306,"passed_time":2.386454807,"remaining_time":5.387013619},
{"learn":[572.2603031],"iteration":307,"passed_time":2.393223083,"remaining_time":5.376981733},
{"learn":[571.9766756],"iteration":308,"passed_time":2.405714879,"remaining_time":5.379770167},
{"learn":[571.8612809],"iteration":309,"passed_time":2.413219382,"remaining_time":5.371359269},
{"learn":[571.7228616],"iteration":310,"passed_time":2.421033915,"remaining_time":5.363641054},
{"learn":[571.6603849],"iteration":311,"passed_time":2.426476361,"remaining_time":5.350691462},
{"learn":[571.5578102],"iteration":312,"passed_time":2.433477505,"remaining_time":5.341211009},
{"learn":[571.4669027],"iteration":313,"passed_time":2.440321029,"remaining_time":5.331401993},
{"learn":[571.3498344],"iteration":314,"passed_time":2.447657078,"remaining_time":5.322682853},
{"learn":[571.3063143],"iteration":315,"passed_time":2.452876531,"remaining_time":5.309390972},
{"learn":[571.2834193],"iteration":316,"passed_time":2.458883541,"remaining_time":5.297846872},
{"learn":[571.1059154],"iteration":317,"passed_time":2.468028239,"remaining_time":5.293066852},
{"learn":[570.9864978],"iteration":318,"passed_time":2.475788983,"remaining_time":5.285305007},
{"learn":[570.9497453],"iteration":319,"passed_time":2.481553418,"remaining_time":5.273301013},
{"learn":[570.8479756],"iteration":320,"passed_time":2.489196582,"remaining_time":5.265309904},
{"learn":[570.7906698],"iteration":321,"passed_time":2.496111687,"remaining_time":5.255787962},
{"learn":[570.7257399],"iteration":322,"passed_time":2.502805633,"remaining_time":5.245818617},
{"learn":[570.647725],"iteration":323,"passed_time":2.510384216,"remaining_time":5.237715216},
{"learn":[570.5304023],"iteration":324,"passed_time":2.518733274,"remaining_time":5.231215261},
{"learn":[570.4608144],"iteration":325,"passed_time":2.524627454,"remaining_time":5.21962854},
{"learn":[570.3540202],"iteration":326,"passed_time":2.532405072,"remaining_time":5.211952947},
{"learn":[570.204779],"iteration":327,"passed_time":2.539802953,"remaining_time":5.203498733},
{"learn":[570.0877185],"iteration":328,"passed_time":2.549587172,"remaining_time":5.19991791},
{"learn":[569.950985],"iteration":329,"passed_time":2.556035917,"remaining_time":5.189527469},
{"learn":[569.7189188],"iteration":330,"passed_time":2.567275588,"remaining_time":5.188844013},
{"learn":[569.5985095],"iteration":331,"passed_time":2.574961793,"remaining_time":5.180947221},
{"learn":[569.4805948],"iteration":332,"passed_time":2.583497136,"remaining_time":5.174752521},
{"learn":[569.4147679],"iteration":333,"passed_time":2.589957256,"remaining_time":5.164405786},
{"learn":[569.2862921],"iteration":334,"passed_time":2.598311813,"remaining_time":5.157842854},
{"learn":[569.1840611],"iteration":335,"passed_time":2.605302958,"remaining_time":5.148574893},
{"learn":[569.0039037],"iteration":336,"passed_time":2.614272953,"remaining_time":5.143213555},
{"learn":[568.9477079],"iteration":337,"passed_time":2.622169193,"remaining_time":5.135727827},
{"learn":[568.9301629],"iteration":338,"passed_time":2.628838014,"remaining_time":5.125846393},
{"learn":[568.8901417],"iteration":339,"passed_time":2.635228637,"remaining_time":5.115443824},
{"learn":[568.8568851],"iteration":340,"passed_time":2.641317352,"remaining_time":5.104481335},
{"learn":[568.735086],"iteration":341,"passed_time":2.647917509,"remaining_time":5.094531348},
{"learn":[568.6078318],"iteration":342,"passed_time":2.655803957,"remaining_time":5.087064723},
{"learn":[568.511466],"iteration":343,"passed_time":2.662728354,"remaining_time":5.077761047},
{"learn":[568.4301608],"iteration":344,"passed_time":2.669188141,"remaining_time":5.067589078},
{"learn":[568.2772112],"iteration":345,"passed_time":2.676987258,"remaining_time":5.059970135},
{"learn":[568.2262188],"iteration":346,"passed_time":2.682962603,"remaining_time":5.048918096},
{"learn":[568.1769835],"iteration":347,"passed_time":2.688594417,"remaining_time":5.037251608},
{"learn":[567.9820843],"iteration":348,"passed_time":2.696817104,"remaining_time":5.030452534},
{"learn":[567.9282813],"iteration":349,"passed_time":2.703455051,"remaining_time":5.020702238},
{"learn":[567.7995088],"iteration":350,"passed_time":2.710945095,"remaining_time":5.012545205},
{"learn":[567.7137415],"iteration":351,"passed_time":2.717740205,"remaining_time":5.003112649},
{"learn":[567.6054192],"iteration":352,"passed_time":2.726447292,"remaining_time":4.997199428},
{"learn":[567.571948],"iteration":353,"passed_time":2.732410262,"remaining_time":4.986262794},
{"learn":[567.3640052],"iteration":354,"passed_time":2.742611217,"remaining_time":4.983054183},
{"learn":[567.1656885],"iteration":355,"passed_time":2.753088621,"remaining_time":4.980306382},
{"learn":[567.0282919],"iteration":356,"passed_time":2.762370106,"remaining_time":4.975361284},
{"learn":[566.8629102],"iteration":357,"passed_time":2.771279854,"remaining_time":4.969725324},
{"learn":[566.811336],"iteration":358,"passed_time":2.778087754,"remaining_time":4.960318246},
{"learn":[566.7437477],"iteration":359,"passed_time":2.78514448,"remaining_time":4.951367964},
{"learn":[566.6408631],"iteration":360,"passed_time":2.791784219,"remaining_time":4.941690071},
{"learn":[566.4934957],"iteration":361,"passed_time":2.80147644,"remaining_time":4.937408754},
{"learn":[566.4102297],"iteration":362,"passed_time":2.80957634,"remaining_time":4.930303384},
{"learn":[566.1878286],"iteration":363,"passed_time":2.819434389,"remaining_time":4.926264482},
{"learn":[566.1538023],"iteration":364,"passed_time":2.826457991,"remaining_time":4.917262532},
{"learn":[566.0742246],"iteration":365,"passed_time":2.834784758,"remaining_time":4.910528788},
{"learn":[566.0183652],"iteration":366,"passed_time":2.840679021,"remaining_time":4.899590792},
{"learn":[565.9870308],"iteration":367,"passed_time":2.847063686,"remaining_time":4.889522417},
{"learn":[565.9516395],"iteration":368,"passed_time":2.853219732,"remaining_time":4.879083065},
{"learn":[565.896283],"iteration":369,"passed_time":2.859439194,"remaining_time":4.868774843},
{"learn":[565.7829386],"iteration":370,"passed_time":2.868205488,"remaining_time":4.862806608},
{"learn":[565.6398373],"iteration":371,"passed_time":2.875637992,"remaining_time":4.854571664},
{"learn":[565.550478],"iteration":372,"passed_time":2.882001074,"remaining_time":4.84454336},
{"learn":[565.2886737],"iteration":373,"passed_time":2.893328742,"remaining_time":4.842844364},
{"learn":[565.2511074],"iteration":374,"passed_time":2.899568577,"remaining_time":4.832614296},
{"learn":[565.1967763],"iteration":375,"passed_time":2.90626244,"remaining_time":4.823158943},
{"learn":[565.0288871],"iteration":376,"passed_time":2.914928237,"remaining_time":4.816976901},
{"learn":[564.9462811],"iteration":377,"passed_time":2.92216154,"remaining_time":4.808424545},
{"learn":[564.9042221],"iteration":378,"passed_time":2.928784696,"remaining_time":4.79887941},
{"learn":[564.746181],"iteration":379,"passed_time":2.936680269,"remaining_time":4.791425702},
{"learn":[564.6368209],"iteration":380,"passed_time":2.944403056,"remaining_time":4.783688954},
{"learn":[564.5996616],"iteration":381,"passed_time":2.950762346,"remaining_time":4.773746413},
{"learn":[564.5088869],"iteration":382,"passed_time":2.957972691,"remaining_time":4.765193604},
{"learn":[564.4796376],"iteration":383,"passed_time":2.963585381,"remaining_time":4.754084882},
{"learn":[564.4270107],"iteration":384,"passed_time":2.970137956,"remaining_time":4.744506086},
{"learn":[564.3549629],"iteration":385,"passed_time":2.977693207,"remaining_time":4.736537899},
{"learn":[564.264946],"iteration":386,"passed_time":2.984947717,"remaining_time":4.72809548},
{"learn":[564.1795054],"iteration":387,"passed_time":2.99177295,"remaining_time":4.718982076},
{"learn":[564.1255878],"iteration":388,"passed_time":2.99881576,"remaining_time":4.710222183},
{"learn":[564.086858],"iteration":389,"passed_time":3.004413658,"remaining_time":4.699211106},
{"learn":[563.971008],"iteration":390,"passed_time":3.012291731,"remaining_time":4.691779193},
{"learn":[563.903285],"iteration":391,"passed_time":3.018785184,"remaining_time":4.682197428},
{"learn":[563.8575551],"iteration":392,"passed_time":3.025561835,"remaining_time":4.673068788},
{"learn":[563.7708914],"iteration":393,"passed_time":3.033108794,"remaining_time":4.665136876},
{"learn":[563.7002101],"iteration":394,"passed_time":3.039727992,"remaining_time":4.655785912},
{"learn":[563.5410691],"iteration":395,"passed_time":3.048631157,"remaining_time":4.649932371},
{"learn":[563.453473],"iteration":396,"passed_time":3.055838586,"remaining_time":4.641487826},
{"learn":[563.4065108],"iteration":397,"passed_time":3.06202934,"remaining_time":4.631511715},
{"learn":[563.2754875],"iteration":398,"passed_time":3.070156405,"remaining_time":4.624471176},
{"learn":[563.1599159],"iteration":399,"passed_time":3.078242096,"remaining_time":4.617363144},
{"learn":[563.1176435],"iteration":400,"passed_time":3.084817337,"remaining_time":4.607993978},
{"learn":[563.0084953],"iteration":401,"passed_time":3.091316331,"remaining_time":4.598525289},
{"learn":[562.7931097],"iteration":402,"passed_time":3.101098842,"remaining_time":4.593935505},
{"learn":[562.7325448],"iteration":403,"passed_time":3.108117068,"remaining_time":4.585242012},
{"learn":[562.6646197],"iteration":404,"passed_time":3.114686435,"remaining_time":4.575897355},
{"learn":[562.5413901],"iteration":405,"passed_time":3.12346077,"remaining_time":4.569792358},
{"learn":[562.4973242],"iteration":406,"passed_time":3.128957005,"remaining_time":4.558898045},
{"learn":[562.3620763],"iteration":407,"passed_time":3.137563346,"remaining_time":4.552542895},
{"learn":[562.2007737],"iteration":408,"passed_time":3.146761543,"remaining_time":4.54703196},
{"learn":[562.1453299],"iteration":409,"passed_time":3.15345978,"remaining_time":4.537905537},
{"learn":[562.0585173],"iteration":410,"passed_time":3.161517805,"remaining_time":4.530739629},
{"learn":[562.0185482],"iteration":411,"passed_time":3.168557365,"remaining_time":4.522115851},
{"learn":[561.9373958],"iteration":412,"passed_time":3.175407555,"remaining_time":4.513230593},
{"learn":[561.8613704],"iteration":413,"passed_time":3.182944682,"remaining_time":4.505327496},
{"learn":[561.6663241],"iteration":414,"passed_time":3.191959842,"remaining_time":4.499509657},
{"learn":[561.5408051],"iteration":415,"passed_time":3.19879795,"remaining_time":4.490620199},
{"learn":[561.4275251],"iteration":416,"passed_time":3.206145291,"remaining_time":4.482452529},
{"learn":[561.3044464],"iteration":417,"passed_time":3.214832504,"remaining_time":4.476154348},
{"learn":[561.2156426],"iteration":418,"passed_time":3.221844272,"remaining_time":4.467521533},
{"learn":[561.1630746],"iteration":419,"passed_time":3.228815709,"remaining_time":4.458840741},
{"learn":[561.1105547],"iteration":420,"passed_time":3.234773137,"remaining_time":4.448773507},
{"learn":[561.028708],"iteration":421,"passed_time":3.240625736,"remaining_time":4.438582169},
{"learn":[560.849574],"iteration":422,"passed_time":3.250517993,"remaining_time":4.433921706},
{"learn":[560.7775402],"iteration":423,"passed_time":3.25685595,"remaining_time":4.424408083},
{"learn":[560.7045524],"iteration":424,"passed_time":3.264893935,"remaining_time":4.417209441},
{"learn":[560.6083419],"iteration":425,"passed_time":3.271661253,"remaining_time":4.40829474},
{"learn":[560.4961012],"iteration":426,"passed_time":3.279794901,"remaining_time":4.401223603},
{"learn":[560.452062],"iteration":427,"passed_time":3.286156483,"remaining_time":4.391779225},
{"learn":[560.3685333],"iteration":428,"passed_time":3.293780814,"remaining_time":4.384029942},
{"learn":[560.2666509],"iteration":429,"passed_time":3.301172987,"remaining_time":4.375973495},
{"learn":[560.2136615],"iteration":430,"passed_time":3.307183039,"remaining_time":4.366095473},
{"learn":[560.1642629],"iteration":431,"passed_time":3.313415833,"remaining_time":4.356528225},
{"learn":[560.0404149],"iteration":432,"passed_time":3.320810464,"remaining_time":4.348497767},
{"learn":[559.9697713],"iteration":433,"passed_time":3.327286667,"remaining_time":4.339272473},
{"learn":[559.9239662],"iteration":434,"passed_time":3.334588426,"remaining_time":4.331132093},
{"learn":[559.8147279],"iteration":435,"passed_time":3.342885902,"remaining_time":4.324283598},
{"learn":[559.7644516],"iteration":436,"passed_time":3.350086248,"remaining_time":4.316015005},
{"learn":[559.7063367],"iteration":437,"passed_time":3.35795353,"remaining_time":4.30860704},
{"learn":[559.6456804],"iteration":438,"passed_time":3.364586269,"remaining_time":4.299619355},
{"learn":[559.537393],"iteration":439,"passed_time":3.372684377,"remaining_time":4.292507388},
{"learn":[559.4868779],"iteration":440,"passed_time":3.379362698,"remaining_time":4.283591265},
{"learn":[559.4099987],"iteration":441,"passed_time":3.385774736,"remaining_time":4.274349101},
{"learn":[559.2429502],"iteration":442,"passed_time":3.39508547,"remaining_time":4.26876435},
{"learn":[559.1238907],"iteration":443,"passed_time":3.40266747,"remaining_time":4.260998003},
{"learn":[559.0363514],"iteration":444,"passed_time":3.410457796,"remaining_time":4.253492308},
{"learn":[558.9515612],"iteration":445,"passed_time":3.417446982,"remaining_time":4.244990198},
{"learn":[558.9087817],"iteration":446,"passed_time":3.422809139,"remaining_time":4.234481999},
{"learn":[558.8532883],"iteration":447,"passed_time":3.429580332,"remaining_time":4.225732909},
{"learn":[558.7827648],"iteration":448,"passed_time":3.436852925,"remaining_time":4.217607933},
{"learn":[558.6748259],"iteration":449,"passed_time":3.445177775,"remaining_time":4.210772836},
{"learn":[558.5973765],"iteration":450,"passed_time":3.451758141,"remaining_time":4.201807582},
{"learn":[558.4890965],"iteration":451,"passed_time":3.45996637,"remaining_time":4.194826484},
{"learn":[558.4372796],"iteration":452,"passed_time":3.466226039,"remaining_time":4.185487071},
{"learn":[558.3385116],"iteration":453,"passed_time":3.473965075,"remaining_time":4.177940377},
{"learn":[558.2413242],"iteration":454,"passed_time":3.481615031,"remaining_time":4.170286136},
{"learn":[558.1186423],"iteration":455,"passed_time":3.489045952,"remaining_time":4.16237061},
{"learn":[557.9886844],"iteration":456,"passed_time":3.498352895,"remaining_time":4.156686262},
{"learn":[557.8475976],"iteration":457,"passed_time":3.507665171,"remaining_time":4.150992407},
{"learn":[557.7101385],"iteration":458,"passed_time":3.516008937,"remaining_time":4.144141253},
{"learn":[557.6743019],"iteration":459,"passed_time":3.521846411,"remaining_time":4.134341439},
{"learn":[557.6327838],"iteration":460,"passed_time":3.528822514,"remaining_time":4.125890098},
{"learn":[557.5705716],"iteration":461,"passed_time":3.535407213,"remaining_time":4.116989352},
{"learn":[557.5220806],"iteration":462,"passed_time":3.541416723,"remaining_time":4.107431491},
{"learn":[557.4857129],"iteration":463,"passed_time":3.547240156,"remaining_time":4.097673974},
{"learn":[557.3390672],"iteration":464,"passed_time":3.556279941,"remaining_time":4.091633911},
{"learn":[557.2535877],"iteration":465,"passed_time":3.563742236,"remaining_time":4.083773292},
{"learn":[557.1631838],"iteration":466,"passed_time":3.569623501,"remaining_time":4.074109905},
{"learn":[557.1060371],"iteration":467,"passed_time":3.576078746,"remaining_time":4.065115156},
{"learn":[557.0389911],"iteration":468,"passed_time":3.583019475,"remaining_time":4.056680898},
{"learn":[556.9177264],"iteration":469,"passed_time":3.590242612,"remaining_time":4.048571456},
{"learn":[556.815855],"iteration":470,"passed_time":3.598110019,"remaining_time":4.041189384},
{"learn":[556.7782987],"iteration":471,"passed_time":3.604187318,"remaining_time":4.031802763},
{"learn":[556.6843048],"iteration":472,"passed_time":3.612070974,"remaining_time":4.024442714},
{"learn":[556.5932854],"iteration":473,"passed_time":3.620938348,"remaining_time":4.018172091},
{"learn":[556.5307394],"iteration":474,"passed_time":3.62831298,"remaining_time":4.010240662},
{"learn":[556.4869946],"iteration":475,"passed_time":3.635220377,"remaining_time":4.001797222},
{"learn":[556.4024032],"iteration":476,"passed_time":3.641898448,"remaining_time":3.993108781},
{"learn":[556.3203726],"iteration":477,"passed_time":3.649300037,"remaining_time":3.985218869},
{"learn":[556.269942],"iteration":478,"passed_time":3.655258965,"remaining_time":3.975761839},
{"learn":[556.142011],"iteration":479,"passed_time":3.664451495,"remaining_time":3.969822453},
{"learn":[556.0745001],"iteration":480,"passed_time":3.671312644,"remaining_time":3.961353975},
{"learn":[556.017182],"iteration":481,"passed_time":3.677515856,"remaining_time":3.95218509},
{"learn":[555.932109],"iteration":482,"passed_time":3.685443427,"remaining_time":3.944874228},
{"learn":[555.6905126],"iteration":483,"passed_time":3.695006487,"remaining_time":3.939304436},
{"learn":[555.6375432],"iteration":484,"passed_time":3.700824086,"remaining_time":3.92974104},
{"learn":[555.5519363],"iteration":485,"passed_time":3.708255591,"remaining_time":3.921899946},
{"learn":[555.5234873],"iteration":486,"passed_time":3.713443003,"remaining_time":3.911696634},
{"learn":[555.367079],"iteration":487,"passed_time":3.72216759,"remaining_time":3.905225013},
{"learn":[555.2511832],"iteration":488,"passed_time":3.730690642,"remaining_time":3.898533575},
{"learn":[555.1350589],"iteration":489,"passed_time":3.738583382,"remaining_time":3.891178622},
{"learn":[555.0449373],"iteration":490,"passed_time":3.745152206,"remaining_time":3.882449029},
{"learn":[554.9422786],"iteration":491,"passed_time":3.753844253,"remaining_time":3.875920489},
{"learn":[554.8490401],"iteration":492,"passed_time":3.762305932,"remaining_time":3.869146263},
{"learn":[554.8043147],"iteration":493,"passed_time":3.768929088,"remaining_time":3.860482022},
{"learn":[554.7025664],"iteration":494,"passed_time":3.775801153,"remaining_time":3.852079964},
{"learn":[554.6015699],"iteration":495,"passed_time":3.783714434,"remaining_time":3.844742086},
{"learn":[554.5416399],"iteration":496,"passed_time":3.791186687,"remaining_time":3.83695554},
{"learn":[554.4155],"iteration":497,"passed_time":3.800164099,"remaining_time":3.830687505},
{"learn":[554.2944675],"iteration":498,"passed_time":3.808955767,"remaining_time":3.824222123},
{"learn":[554.2386162],"iteration":499,"passed_time":3.815632297,"remaining_time":3.815632297},
{"learn":[554.1214524],"iteration":500,"passed_time":3.823711988,"remaining_time":3.808447669},
{"learn":[554.0431],"iteration":501,"passed_time":3.831290946,"remaining_time":3.800762732},
{"learn":[553.9569034],"iteration":502,"passed_time":3.839294682,"remaining_time":3.793497927},
{"learn":[553.8771589],"iteration":503,"passed_time":3.847298335,"remaining_time":3.786230107},
{"learn":[553.7009653],"iteration":504,"passed_time":3.856511822,"remaining_time":3.780145251},
{"learn":[553.6420738],"iteration":505,"passed_time":3.861723608,"remaining_time":3.77014123},
{"learn":[553.4901992],"iteration":506,"passed_time":3.871361915,"remaining_time":3.764460403},
{"learn":[553.4058156],"iteration":507,"passed_time":3.878610718,"remaining_time":3.75644975},
{"learn":[553.3174675],"iteration":508,"passed_time":3.884988632,"remaining_time":3.747602001},
{"learn":[553.2594528],"iteration":509,"passed_time":3.891779533,"remaining_time":3.739160728},
{"learn":[553.1523544],"iteration":510,"passed_time":3.900767111,"remaining_time":3.732828018},
{"learn":[553.0866321],"iteration":511,"passed_time":3.907188483,"remaining_time":3.724039023},
{"learn":[552.9468994],"iteration":512,"passed_time":3.915360463,"remaining_time":3.716921141},
{"learn":[552.8012381],"iteration":513,"passed_time":3.923857141,"remaining_time":3.710106168},
{"learn":[552.7186103],"iteration":514,"passed_time":3.931284521,"remaining_time":3.702277655},
{"learn":[552.601671],"iteration":515,"passed_time":3.939885112,"remaining_time":3.695551151},
{"learn":[552.5367386],"iteration":516,"passed_time":3.946127322,"remaining_time":3.686614113},
{"learn":[552.4977062],"iteration":517,"passed_time":3.951826468,"remaining_time":3.677182157},
{"learn":[552.3881913],"iteration":518,"passed_time":3.958703699,"remaining_time":3.668856415},
{"learn":[552.2980946],"iteration":519,"passed_time":3.966143495,"remaining_time":3.661055534},
{"learn":[552.1323276],"iteration":520,"passed_time":3.973474795,"remaining_time":3.653156289},
{"learn":[552.0317049],"iteration":521,"passed_time":3.982385292,"remaining_time":3.646705306},
{"learn":[551.7914619],"iteration":522,"passed_time":3.992759033,"remaining_time":3.641579462},
{"learn":[551.7477604],"iteration":523,"passed_time":3.998446012,"remaining_time":3.632176148},
{"learn":[551.7068342],"iteration":524,"passed_time":4.004458772,"remaining_time":3.623081746},
{"learn":[551.6806794],"iteration":525,"passed_time":4.011254714,"remaining_time":3.614704818},
{"learn":[551.6559701],"iteration":526,"passed_time":4.017600963,"remaining_time":3.605930276},
{"learn":[551.6081081],"iteration":527,"passed_time":4.024149247,"remaining_time":3.597345539},
{"learn":[551.4821164],"iteration":528,"passed_time":4.033670516,"remaining_time":3.591415525},
{"learn":[551.3751694],"iteration":529,"passed_time":4.040539997,"remaining_time":3.583120375},
{"learn":[551.3331797],"iteration":530,"passed_time":4.047947378,"remaining_time":3.575305688},
{"learn":[551.2810243],"iteration":531,"passed_time":4.054222462,"remaining_time":3.566496452},
{"learn":[551.1570624],"iteration":532,"passed_time":4.06242915,"remaining_time":3.559389143},
{"learn":[551.1461846],"iteration":533,"passed_time":4.068557739,"remaining_time":3.550464244},
{"learn":[550.9975466],"iteration":534,"passed_time":4.077554692,"remaining_time":3.544042863},
{"learn":[550.9070395],"iteration":535,"passed_time":4.084326635,"remaining_time":3.535685744},
{"learn":[550.833945],"iteration":536,"passed_time":4.091840846,"remaining_time":3.527974509},
{"learn":[550.7567027],"iteration":537,"passed_time":4.099208936,"remaining_time":3.520138528},
{"learn":[550.5872884],"iteration":538,"passed_time":4.107906024,"remaining_time":3.513440959},
{"learn":[550.5384237],"iteration":539,"passed_time":4.114986207,"remaining_time":3.50535862},
{"learn":[550.4709109],"iteration":540,"passed_time":4.120814806,"remaining_time":3.496218107},
{"learn":[550.2586257],"iteration":541,"passed_time":4.131441705,"remaining_time":3.491144467},
{"learn":[550.108239],"iteration":542,"passed_time":4.1409501,"remaining_time":3.485109016},
{"learn":[550.0544979],"iteration":543,"passed_time":4.147983284,"remaining_time":3.476985988},
{"learn":[550.0255796],"iteration":544,"passed_time":4.153913963,"remaining_time":3.46794652},
{"learn":[549.9989441],"iteration":545,"passed_time":4.16003147,"remaining_time":3.459073786},
{"learn":[549.917046],"iteration":546,"passed_time":4.166567254,"remaining_time":3.450557525},
{"learn":[549.7878484],"iteration":547,"passed_time":4.175253926,"remaining_time":3.443822581},
{"learn":[549.6928102],"iteration":548,"passed_time":4.183100542,"remaining_time":3.436390427},
{"learn":[549.6305154],"iteration":549,"passed_time":4.190422258,"remaining_time":3.428527302},
{"learn":[549.5819077],"iteration":550,"passed_time":4.196685093,"remaining_time":3.419803279},
{"learn":[549.5319117],"iteration":551,"passed_time":4.203437912,"remaining_time":3.411485842},
{"learn":[549.4482456],"iteration":552,"passed_time":4.211126866,"remaining_time":3.403930758},
{"learn":[549.3845762],"iteration":553,"passed_time":4.218645535,"remaining_time":3.396238102},
{"learn":[549.3416164],"iteration":554,"passed_time":4.224501342,"remaining_time":3.387212787},
{"learn":[549.2459326],"iteration":555,"passed_time":4.23193043,"remaining_time":3.379455235},
{"learn":[549.211287],"iteration":556,"passed_time":4.238453964,"remaining_time":3.370978647},
{"learn":[549.1293126],"iteration":557,"passed_time":4.24459197,"remaining_time":3.362203675},
{"learn":[549.0737019],"iteration":558,"passed_time":4.251030674,"remaining_time":3.353675362},
{"learn":[548.95408],"iteration":559,"passed_time":4.260669648,"remaining_time":3.347669009},
{"learn":[548.887388],"iteration":560,"passed_time":4.267042687,"remaining_time":3.33909401},
{"learn":[548.7975783],"iteration":561,"passed_time":4.276434502,"remaining_time":3.332879559},
{"learn":[548.711733],"iteration":562,"passed_time":4.28335519,"remaining_time":3.324735734},
{"learn":[548.6985712],"iteration":563,"passed_time":4.289705148,"remaining_time":3.316155043},
{"learn":[548.6608853],"iteration":564,"passed_time":4.295671492,"remaining_time":3.307286901},
{"learn":[548.6074933],"iteration":565,"passed_time":4.302217943,"remaining_time":3.298873829},
{"learn":[548.5008688],"iteration":566,"passed_time":4.308861807,"remaining_time":3.290541733},
{"learn":[548.4052017],"iteration":567,"passed_time":4.316959081,"remaining_time":3.283320991},
{"learn":[548.3392691],"iteration":568,"passed_time":4.323660193,"remaining_time":3.275039619},
{"learn":[548.2335838],"iteration":569,"passed_time":4.331988543,"remaining_time":3.267991357},
{"learn":[548.1706671],"iteration":570,"passed_time":4.340862084,"remaining_time":3.261348221},
{"learn":[548.0880777],"iteration":571,"passed_time":4.347631485,"remaining_time":3.25312286},
{"learn":[548.018424],"iteration":572,"passed_time":4.355962794,"remaining_time":3.246066515},
{"learn":[547.948806],"iteration":573,"passed_time":4.363373049,"remaining_time":3.238322158},
{"learn":[547.8430285],"iteration":574,"passed_time":4.371213332,"remaining_time":3.230896811},
{"learn":[547.7649227],"iteration":575,"passed_time":4.378453801,"remaining_time":3.223028493},
{"learn":[547.5597265],"iteration":576,"passed_time":4.38783795,"remaining_time":3.216733887},
{"learn":[547.3980377],"iteration":577,"passed_time":4.397634585,"remaining_time":3.210729749},
{"learn":[547.3540721],"iteration":578,"passed_time":4.404530774,"remaining_time":3.202603551},
{"learn":[547.2501833],"iteration":579,"passed_time":4.412448262,"remaining_time":3.195221156},
{"learn":[547.2055798],"iteration":580,"passed_time":4.418598351,"remaining_time":3.186562322},
{"learn":[547.1225312],"iteration":581,"passed_time":4.426884078,"remaining_time":3.179445953},
{"learn":[547.0694901],"iteration":582,"passed_time":4.433359114,"remaining_time":3.171030447},
{"learn":[546.930221],"iteration":583,"passed_time":4.441415931,"remaining_time":3.163748335},
{"learn":[546.8305888],"iteration":584,"passed_time":4.449027847,"remaining_time":3.15614796},
{"learn":[546.7711078],"iteration":585,"passed_time":4.456427811,"remaining_time":3.148397805},
{"learn":[546.7338879],"iteration":586,"passed_time":4.462151997,"remaining_time":3.139469804},
{"learn":[546.6550124],"iteration":587,"passed_time":4.469855201,"remaining_time":3.131939358},
{"learn":[546.5484583],"iteration":588,"passed_time":4.478390252,"remaining_time":3.124988784},
{"learn":[546.4196408],"iteration":589,"passed_time":4.487241085,"remaining_time":3.11825228},
{"learn":[546.3351445],"iteration":590,"passed_time":4.495033328,"remaining_time":3.110776026},
{"learn":[546.274661],"iteration":591,"passed_time":4.501737482,"remaining_time":3.102548805},
{"learn":[546.1962228],"iteration":592,"passed_time":4.509597264,"remaining_time":3.095119876},
{"learn":[546.0405925],"iteration":593,"passed_time":4.518530219,"remaining_time":3.088423012},
{"learn":[545.9318045],"iteration":594,"passed_time":4.526970315,"remaining_time":3.081383156},
{"learn":[545.828286],"iteration":595,"passed_time":4.535688028,"remaining_time":3.074526784},
{"learn":[545.7219934],"iteration":596,"passed_time":4.545748779,"remaining_time":3.068570784},
{"learn":[545.5515955],"iteration":597,"passed_time":4.555066596,"remaining_time":3.062101625},
{"learn":[545.4877596],"iteration":598,"passed_time":4.562895255,"remaining_time":3.054626039},
{"learn":[545.4098928],"iteration":599,"passed_time":4.570619416,"remaining_time":3.047079611},
{"learn":[545.3703783],"iteration":600,"passed_time":4.577684308,"remaining_time":3.039094907},
{"learn":[545.2356562],"iteration":601,"passed_time":4.587168703,"remaining_time":3.032712864},
{"learn":[545.1654538],"iteration":602,"passed_time":4.593643865,"remaining_time":3.024339327},
{"learn":[545.0283258],"iteration":603,"passed_time":4.601430274,"remaining_time":3.016831769},
{"learn":[544.8991223],"iteration":604,"passed_time":4.610898087,"remaining_time":3.010421065},
{"learn":[544.7793884],"iteration":605,"passed_time":4.6193416,"remaining_time":3.003334307},
{"learn":[544.6973024],"iteration":606,"passed_time":4.627525496,"remaining_time":2.996074992},
{"learn":[544.6046046],"iteration":607,"passed_time":4.635647895,"remaining_time":2.988772985},
{"learn":[544.4928424],"iteration":608,"passed_time":4.644044034,"remaining_time":2.981644035},
{"learn":[544.3176273],"iteration":609,"passed_time":4.653356143,"remaining_time":2.975096551},
{"learn":[544.2377111],"iteration":610,"passed_time":4.660827564,"remaining_time":2.967368121},
{"learn":[544.1489218],"iteration":611,"passed_time":4.668386022,"remaining_time":2.959695714},
{"learn":[544.0971015],"iteration":612,"passed_time":4.675801861,"remaining_time":2.951933638},
{"learn":[543.904733],"iteration":613,"passed_time":4.684786773,"remaining_time":2.945159111},
{"learn":[543.7870928],"iteration":614,"passed_time":4.692591807,"remaining_time":2.937638773},
{"learn":[543.7032079],"iteration":615,"passed_time":4.69972303,"remaining_time":2.929697473},
{"learn":[543.5635762],"iteration":616,"passed_time":4.708527531,"remaining_time":2.922797478},
{"learn":[543.4716515],"iteration":617,"passed_time":4.715648462,"remaining_time":2.914850668},
{"learn":[543.3656666],"iteration":618,"passed_time":4.723827151,"remaining_time":2.907557584},
{"learn":[543.2526701],"iteration":619,"passed_time":4.7316611,"remaining_time":2.900050352},
{"learn":[543.2127479],"iteration":620,"passed_time":4.737473575,"remaining_time":2.891308349},
{"learn":[543.1370081],"iteration":621,"passed_time":4.746233119,"remaining_time":2.884366751},
{"learn":[543.0850724],"iteration":622,"passed_time":4.753377967,"remaining_time":2.876442205},
{"learn":[543.0263683],"iteration":623,"passed_time":4.76004208,"remaining_time":2.868230484},
{"learn":[542.9394431],"iteration":624,"passed_time":4.767422336,"remaining_time":2.860453402},
{"learn":[542.9212421],"iteration":625,"passed_time":4.773715504,"remaining_time":2.852028112},
{"learn":[542.7704497],"iteration":626,"passed_time":4.783560179,"remaining_time":2.845722403},
{"learn":[542.6337656],"iteration":627,"passed_time":4.792812748,"remaining_time":2.839054685},
{"learn":[542.4977851],"iteration":628,"passed_time":4.800762194,"remaining_time":2.831610134},
{"learn":[542.4793066],"iteration":629,"passed_time":4.807201982,"remaining_time":2.823277354},
{"learn":[542.4106662],"iteration":630,"passed_time":4.815191635,"remaining_time":2.815856915},
{"learn":[542.2768497],"iteration":631,"passed_time":4.826543593,"remaining_time":2.810392472},
{"learn":[542.1387112],"iteration":632,"passed_time":4.83642785,"remaining_time":2.804058485},
{"learn":[542.0532612],"iteration":633,"passed_time":4.844457835,"remaining_time":2.796642851},
{"learn":[541.9276692],"iteration":634,"passed_time":4.853441205,"remaining_time":2.789773291},
{"learn":[541.8048572],"iteration":635,"passed_time":4.861379235,"remaining_time":2.782298807},
{"learn":[541.7408902],"iteration":636,"passed_time":4.868984776,"remaining_time":2.774633396},
{"learn":[541.6469103],"iteration":637,"passed_time":4.878071476,"remaining_time":2.76780858},
{"learn":[541.592707],"iteration":638,"passed_time":4.884131692,"remaining_time":2.759266887},
{"learn":[541.4397102],"iteration":639,"passed_time":4.893028524,"remaining_time":2.752328545},
{"learn":[541.3318445],"iteration":640,"passed_time":4.901810234,"remaining_time":2.745319616},
{"learn":[541.2569297],"iteration":641,"passed_time":4.908767796,"remaining_time":2.737287961},
{"learn":[541.1591717],"iteration":642,"passed_time":4.916602579,"remaining_time":2.729746688},
{"learn":[541.0495137],"iteration":643,"passed_time":4.925262251,"remaining_time":2.722660499},
{"learn":[540.9364525],"iteration":644,"passed_time":4.93318599,"remaining_time":2.715164382},
{"learn":[540.8476667],"iteration":645,"passed_time":4.939984807,"remaining_time":2.707050498},
{"learn":[540.790914],"iteration":646,"passed_time":4.948343573,"remaining_time":2.699791779},
{"learn":[540.6543151],"iteration":647,"passed_time":4.95746373,"remaining_time":2.692943261},
{"learn":[540.5781647],"iteration":648,"passed_time":4.965010272,"remaining_time":2.68523668},
{"learn":[540.5043445],"iteration":649,"passed_time":4.972382112,"remaining_time":2.677436522},
{"learn":[540.4147446],"iteration":650,"passed_time":4.980330558,"remaining_time":2.669946797},
{"learn":[540.3545736],"iteration":651,"passed_time":4.987255497,"remaining_time":2.661909375},
{"learn":[540.2403649],"iteration":652,"passed_time":4.995234025,"remaining_time":2.654435232},
{"learn":[540.1498385],"iteration":653,"passed_time":5.002166046,"remaining_time":2.64640589},
{"learn":[540.101056],"iteration":654,"passed_time":5.00866079,"remaining_time":2.638149576},
{"learn":[540.0461999],"iteration":655,"passed_time":5.015190824,"remaining_time":2.62991714},
{"learn":[539.893675],"iteration":656,"passed_time":5.023395012,"remaining_time":2.62256391},
{"learn":[539.8135653],"iteration":657,"passed_time":5.03133225,"remaining_time":2.615069346},
{"learn":[539.7609603],"iteration":658,"passed_time":5.039632101,"remaining_time":2.607761072},
{"learn":[539.6469198],"iteration":659,"passed_time":5.048005241,"remaining_time":2.600487548},
{"learn":[539.6097992],"iteration":660,"passed_time":5.055005343,"remaining_time":2.592506523},
{"learn":[539.541294],"iteration":661,"passed_time":5.061751746,"remaining_time":2.584398928},
{"learn":[539.4946259],"iteration":662,"passed_time":5.068547688,"remaining_time":2.57632062},
{"learn":[539.3731855],"iteration":663,"passed_time":5.077601181,"remaining_time":2.569388549},
{"learn":[539.2518197],"iteration":664,"passed_time":5.085619041,"remaining_time":2.561928389},
{"learn":[539.1677516],"iteration":665,"passed_time":5.092681558,"remaining_time":2.553987448},
{"learn":[539.0233195],"iteration":666,"passed_time":5.101375438,"remaining_time":2.546863599},
{"learn":[538.8858312],"iteration":667,"passed_time":5.109953446,"remaining_time":2.539677461},
{"learn":[538.8423388],"iteration":668,"passed_time":5.116364693,"remaining_time":2.531415117},
{"learn":[538.7094096],"iteration":669,"passed_time":5.124197893,"remaining_time":2.523858664},
{"learn":[538.5797049],"iteration":670,"passed_time":5.134275227,"remaining_time":2.517401713},
{"learn":[538.5040813],"iteration":671,"passed_time":5.142211215,"remaining_time":2.509888807},
{"learn":[538.3975483],"iteration":672,"passed_time":5.149770132,"remaining_time":2.502191431},
{"learn":[538.2348919],"iteration":673,"passed_time":5.160078875,"remaining_time":2.4958245},
{"learn":[538.1338197],"iteration":674,"passed_time":5.167551212,"remaining_time":2.488080213},
{"learn":[537.9904786],"iteration":675,"passed_time":5.176758741,"remaining_time":2.481168391},
{"learn":[537.8579182],"iteration":676,"passed_time":5.187129149,"remaining_time":2.474804601},
{"learn":[537.6990376],"iteration":677,"passed_time":5.196349178,"remaining_time":2.467882648},
{"learn":[537.537491],"iteration":678,"passed_time":5.206242893,"remaining_time":2.461272413},
{"learn":[537.4549051],"iteration":679,"passed_time":5.213098125,"remaining_time":2.453222647},
{"learn":[537.403636],"iteration":680,"passed_time":5.221031446,"remaining_time":2.445681397},
{"learn":[537.3649737],"iteration":681,"passed_time":5.227352529,"remaining_time":2.43738725},
{"learn":[537.2950123],"iteration":682,"passed_time":5.235413763,"remaining_time":2.429906534},
{"learn":[537.2364591],"iteration":683,"passed_time":5.241810427,"remaining_time":2.42165511},
{"learn":[537.2146435],"iteration":684,"passed_time":5.24838146,"remaining_time":2.413489285},
{"learn":[537.1380163],"iteration":685,"passed_time":5.256226701,"remaining_time":2.405911347},
{"learn":[537.0552387],"iteration":686,"passed_time":5.26372237,"remaining_time":2.398173365},
{"learn":[536.9092377],"iteration":687,"passed_time":5.272474581,"remaining_time":2.391005915},
{"learn":[536.8807083],"iteration":688,"passed_time":5.279025699,"remaining_time":2.382840337},
{"learn":[536.7969927],"iteration":689,"passed_time":5.288092108,"remaining_time":2.375809498},
{"learn":[536.7113934],"iteration":690,"passed_time":5.296592869,"remaining_time":2.368519821},
{"learn":[536.6842587],"iteration":691,"passed_time":5.303251232,"remaining_time":2.360406618},
{"learn":[536.6006054],"iteration":692,"passed_time":5.310050008,"remaining_time":2.352359816},
{"learn":[536.4806592],"iteration":693,"passed_time":5.32023588,"remaining_time":2.345810057},
{"learn":[536.4125225],"iteration":694,"passed_time":5.326452508,"remaining_time":2.337507935},
{"learn":[536.353649],"iteration":695,"passed_time":5.333354447,"remaining_time":2.329511138},
{"learn":[536.2536601],"iteration":696,"passed_time":5.341478762,"remaining_time":2.322048874},
{"learn":[536.1745141],"iteration":697,"passed_time":5.348329203,"remaining_time":2.314033552},
{"learn":[536.0062172],"iteration":698,"passed_time":5.357778807,"remaining_time":2.307140803},
{"learn":[535.916624],"iteration":699,"passed_time":5.364368715,"remaining_time":2.299015163},
{"learn":[535.8501724],"iteration":700,"passed_time":5.370429181,"remaining_time":2.290668082},
{"learn":[535.7994067],"iteration":701,"passed_time":5.378352753,"remaining_time":2.283118405},
{"learn":[535.7352102],"iteration":702,"passed_time":5.385180069,"remaining_time":2.275104524},
{"learn":[535.6189077],"iteration":703,"passed_time":5.394744962,"remaining_time":2.268245041},
{"learn":[535.5693085],"iteration":704,"passed_time":5.403019856,"remaining_time":2.260838096},
{"learn":[535.4964399],"iteration":705,"passed_time":5.409811923,"remaining_time":2.252811197},
{"learn":[535.4724267],"iteration":706,"passed_time":5.415536484,"remaining_time":2.244345389},
{"learn":[535.3445808],"iteration":707,"passed_time":5.424817219,"remaining_time":2.237353994},
{"learn":[535.2563704],"iteration":708,"passed_time":5.432732416,"remaining_time":2.229795674},
{"learn":[535.1563662],"iteration":709,"passed_time":5.443610349,"remaining_time":2.223446481},
{"learn":[535.0751486],"iteration":710,"passed_time":5.452040862,"remaining_time":2.216089746},
{"learn":[535.0532051],"iteration":711,"passed_time":5.457786881,"remaining_time":2.207644132},
{"learn":[534.8840574],"iteration":712,"passed_time":5.467184446,"remaining_time":2.200675927},
{"learn":[534.8524845],"iteration":713,"passed_time":5.47421213,"remaining_time":2.192751638},
{"learn":[534.7521598],"iteration":714,"passed_time":5.482229824,"remaining_time":2.185224475},
{"learn":[534.6730007],"iteration":715,"passed_time":5.490253518,"remaining_time":2.177698323},
{"learn":[534.5121933],"iteration":716,"passed_time":5.499249096,"remaining_time":2.170554385},
{"learn":[534.4723115],"iteration":717,"passed_time":5.50447109,"remaining_time":2.161923186},
{"learn":[534.4413591],"iteration":718,"passed_time":5.508989149,"remaining_time":2.153026357},
{"learn":[534.3402109],"iteration":719,"passed_time":5.518421879,"remaining_time":2.146052953},
{"learn":[534.2022895],"iteration":720,"passed_time":5.528680083,"remaining_time":2.139392154},
{"learn":[534.1335295],"iteration":721,"passed_time":5.535747891,"remaining_time":2.131492955},
{"learn":[534.0589412],"iteration":722,"passed_time":5.542759993,"remaining_time":2.123574714},
{"learn":[533.9981465],"iteration":723,"passed_time":5.549405982,"remaining_time":2.115519407},
{"learn":[533.9170738],"iteration":724,"passed_time":5.558003573,"remaining_time":2.108208252},
{"learn":[533.8542097],"iteration":725,"passed_time":5.565124046,"remaining_time":2.100336073},
{"learn":[533.7378978],"iteration":726,"passed_time":5.575640074,"remaining_time":2.093741046},
{"learn":[533.6323178],"iteration":727,"passed_time":5.583780514,"remaining_time":2.086247664},
{"learn":[533.5809768],"iteration":728,"passed_time":5.59066287,"remaining_time":2.078284825},
{"learn":[533.5665899],"iteration":729,"passed_time":5.596445846,"remaining_time":2.069918326},
{"learn":[533.4871887],"iteration":730,"passed_time":5.604152175,"remaining_time":2.062266669},
{"learn":[533.4496692],"iteration":731,"passed_time":5.610664626,"remaining_time":2.054177759},
{"learn":[533.3231956],"iteration":732,"passed_time":5.61967812,"remaining_time":2.047004172},
{"learn":[533.2437558],"iteration":733,"passed_time":5.626805718,"remaining_time":2.039142127},
{"learn":[533.0799551],"iteration":734,"passed_time":5.636647852,"remaining_time":2.03226079},
{"learn":[532.9669558],"iteration":735,"passed_time":5.6458058,"remaining_time":2.025125993},
{"learn":[532.9398014],"iteration":736,"passed_time":5.652285502,"remaining_time":2.017029969},
{"learn":[532.8913352],"iteration":737,"passed_time":5.659590678,"remaining_time":2.009231379},
{"learn":[532.7319871],"iteration":738,"passed_time":5.67042082,"remaining_time":2.002679072},
{"learn":[532.7008992],"iteration":739,"passed_time":5.677186097,"remaining_time":1.994687007},
{"learn":[532.6100263],"iteration":740,"passed_time":5.683189232,"remaining_time":1.986431864},
{"learn":[532.56489],"iteration":741,"passed_time":5.690025215,"remaining_time":1.978472379},
{"learn":[532.5399187],"iteration":742,"passed_time":5.695848439,"remaining_time":1.970165611},
{"learn":[532.4080414],"iteration":743,"passed_time":5.705233588,"remaining_time":1.963091127},
{"learn":[532.293657],"iteration":744,"passed_time":5.715477208,"remaining_time":1.956304279},
{"learn":[532.2356338],"iteration":745,"passed_time":5.722713511,"remaining_time":1.948484225},
{"learn":[532.1502171],"iteration":746,"passed_time":5.731890083,"remaining_time":1.941322879},
{"learn":[532.0871302],"iteration":747,"passed_time":5.738975266,"remaining_time":1.93345156},
{"learn":[531.9901804],"iteration":748,"passed_time":5.746929836,"remaining_time":1.925873684},
{"learn":[531.9088337],"iteration":749,"passed_time":5.754187264,"remaining_time":1.918062421},
{"learn":[531.8084428],"iteration":750,"passed_time":5.762943308,"remaining_time":1.910749512},
{"learn":[531.7666791],"iteration":751,"passed_time":5.769151478,"remaining_time":1.902592509},
{"learn":[531.7035348],"iteration":752,"passed_time":5.776636856,"remaining_time":1.894859633},
{"learn":[531.6681659],"iteration":753,"passed_time":5.784221355,"remaining_time":1.887159753},
{"learn":[531.60365],"iteration":754,"passed_time":5.790884136,"remaining_time":1.879161077},
{"learn":[531.5377511],"iteration":755,"passed_time":5.797139596,"remaining_time":1.871034473},
{"learn":[531.4786391],"iteration":756,"passed_time":5.804544601,"remaining_time":1.86328182},
{"learn":[531.2772542],"iteration":757,"passed_time":5.815548738,"remaining_time":1.856679149},
{"learn":[531.2563492],"iteration":758,"passed_time":5.821763783,"remaining_time":1.848544231},
{"learn":[531.1921655],"iteration":759,"passed_time":5.829485778,"remaining_time":1.840890246},
{"learn":[530.9133883],"iteration":760,"passed_time":5.842128444,"remaining_time":1.834781469},
{"learn":[530.848513],"iteration":761,"passed_time":5.848235492,"remaining_time":1.826614235},
{"learn":[530.7387209],"iteration":762,"passed_time":5.856260977,"remaining_time":1.819048298},
{"learn":[530.6280874],"iteration":763,"passed_time":5.864021888,"remaining_time":1.811399431},
{"learn":[530.5544448],"iteration":764,"passed_time":5.87103249,"remaining_time":1.803519784},
{"learn":[530.5057151],"iteration":765,"passed_time":5.878530242,"remaining_time":1.795791223},
{"learn":[530.4057242],"iteration":766,"passed_time":5.888008846,"remaining_time":1.788665008},
{"learn":[530.2836335],"iteration":767,"passed_time":5.896002916,"remaining_time":1.781084214},
{"learn":[530.2416421],"iteration":768,"passed_time":5.902694778,"remaining_time":1.773111175},
{"learn":[530.1078362],"iteration":769,"passed_time":5.912485163,"remaining_time":1.766066997},
{"learn":[530.0384064],"iteration":770,"passed_time":5.918803205,"remaining_time":1.75798435},
{"learn":[529.9643666],"iteration":771,"passed_time":5.925636021,"remaining_time":1.750058307},
{"learn":[529.8868305],"iteration":772,"passed_time":5.933694838,"remaining_time":1.742495121},
{"learn":[529.7303088],"iteration":773,"passed_time":5.944595395,"remaining_time":1.735760412},
{"learn":[529.6963735],"iteration":774,"passed_time":5.951372546,"remaining_time":1.727817836},
{"learn":[529.5908984],"iteration":775,"passed_time":5.9598316,"remaining_time":1.720363761},
{"learn":[529.4764842],"iteration":776,"passed_time":5.968068078,"remaining_time":1.712843219},
{"learn":[529.3874378],"iteration":777,"passed_time":5.975570664,"remaining_time":1.705111423},
{"learn":[529.3641151],"iteration":778,"passed_time":5.981529509,"remaining_time":1.696942261},
{"learn":[529.2913732],"iteration":779,"passed_time":5.989437415,"remaining_time":1.689328502},
{"learn":[529.1939483],"iteration":780,"passed_time":5.996899502,"remaining_time":1.681588977},
{"learn":[529.1598101],"iteration":781,"passed_time":6.003008758,"remaining_time":1.67347303},
{"learn":[529.0847205],"iteration":782,"passed_time":6.010792668,"remaining_time":1.665826321},
{"learn":[528.9886971],"iteration":783,"passed_time":6.019261014,"remaining_time":1.65836783},
{"learn":[528.9281137],"iteration":784,"passed_time":6.025414644,"remaining_time":1.650272801},
{"learn":[528.8446951],"iteration":785,"passed_time":6.031951511,"remaining_time":1.642287053},
{"learn":[528.808508],"iteration":786,"passed_time":6.037998395,"remaining_time":1.634172374},
{"learn":[528.7098956],"iteration":787,"passed_time":6.047677159,"remaining_time":1.627040048},
{"learn":[528.6611978],"iteration":788,"passed_time":6.054390812,"remaining_time":1.619108316},
{"learn":[528.6193769],"iteration":789,"passed_time":6.060494277,"remaining_time":1.611017466},
{"learn":[528.4767569],"iteration":790,"passed_time":6.069653683,"remaining_time":1.60373909},
{"learn":[528.443556],"iteration":791,"passed_time":6.075667818,"remaining_time":1.595629932},
{"learn":[528.376326],"iteration":792,"passed_time":6.083672179,"remaining_time":1.588045575},
{"learn":[528.3175816],"iteration":793,"passed_time":6.090990812,"remaining_time":1.580282251},
{"learn":[528.1985407],"iteration":794,"passed_time":6.097742715,"remaining_time":1.572373908},
{"learn":[528.0915061],"iteration":795,"passed_time":6.107024825,"remaining_time":1.565116915},
{"learn":[527.9662055],"iteration":796,"passed_time":6.114684739,"remaining_time":1.557441659},
{"learn":[527.8390249],"iteration":797,"passed_time":6.123127627,"remaining_time":1.549964637},
{"learn":[527.7534024],"iteration":798,"passed_time":6.131192652,"remaining_time":1.542390141},
{"learn":[527.6763577],"iteration":799,"passed_time":6.138245461,"remaining_time":1.534561365},
{"learn":[527.6269275],"iteration":800,"passed_time":6.145701006,"remaining_time":1.526834582},
{"learn":[527.6027474],"iteration":801,"passed_time":6.152877561,"remaining_time":1.519039597},
{"learn":[527.5344207],"iteration":802,"passed_time":6.160862214,"remaining_time":1.511444404},
{"learn":[527.4835405],"iteration":803,"passed_time":6.167355917,"remaining_time":1.503484776},
{"learn":[527.4099132],"iteration":804,"passed_time":6.174961749,"remaining_time":1.495798188},
{"learn":[527.3560294],"iteration":805,"passed_time":6.182421211,"remaining_time":1.488076569},
{"learn":[527.2916103],"iteration":806,"passed_time":6.190207871,"remaining_time":1.480433853},
{"learn":[527.2077874],"iteration":807,"passed_time":6.198861502,"remaining_time":1.472996792},
{"learn":[527.1507275],"iteration":808,"passed_time":6.206866987,"remaining_time":1.465403702},
{"learn":[527.057896],"iteration":809,"passed_time":6.216088683,"remaining_time":1.458094876},
{"learn":[526.9762484],"iteration":810,"passed_time":6.224235164,"remaining_time":1.45053076},
{"learn":[526.893143],"iteration":811,"passed_time":6.232874379,"remaining_time":1.44307929},
{"learn":[526.8521363],"iteration":812,"passed_time":6.239086174,"remaining_time":1.435066561},
{"learn":[526.820661],"iteration":813,"passed_time":6.244737904,"remaining_time":1.426930283},
{"learn":[526.7114165],"iteration":814,"passed_time":6.253557321,"remaining_time":1.419519147},
{"learn":[526.595031],"iteration":815,"passed_time":6.261360272,"remaining_time":1.411875355},
{"learn":[526.5143896],"iteration":816,"passed_time":6.271204405,"remaining_time":1.40468838},
{"learn":[526.454487],"iteration":817,"passed_time":6.278705699,"remaining_time":1.39697364},
{"learn":[526.4214497],"iteration":818,"passed_time":6.285529516,"remaining_time":1.389109698},
{"learn":[526.3442133],"iteration":819,"passed_time":6.293693371,"remaining_time":1.381542447},
{"learn":[526.2828414],"iteration":820,"passed_time":6.300875217,"remaining_time":1.373759639},
{"learn":[526.2279531],"iteration":821,"passed_time":6.308733125,"remaining_time":1.366124691},
{"learn":[526.1756468],"iteration":822,"passed_time":6.315507859,"remaining_time":1.358256247},
{"learn":[526.0694212],"iteration":823,"passed_time":6.323494429,"remaining_time":1.350649296},
{"learn":[525.9956492],"iteration":824,"passed_time":6.330874352,"remaining_time":1.342912741},
{"learn":[525.8893154],"iteration":825,"passed_time":6.339767225,"remaining_time":1.335495759},
{"learn":[525.8005147],"iteration":826,"passed_time":6.349467322,"remaining_time":1.328244071},
{"learn":[525.698803],"iteration":827,"passed_time":6.357711591,"remaining_time":1.32068405},
{"learn":[525.642079],"iteration":828,"passed_time":6.364488993,"remaining_time":1.312819804},
{"learn":[525.6217723],"iteration":829,"passed_time":6.370759994,"remaining_time":1.304854457},
{"learn":[525.5791157],"iteration":830,"passed_time":6.377018537,"remaining_time":1.296890653},
{"learn":[525.5050415],"iteration":831,"passed_time":6.384340587,"remaining_time":1.289145696},
{"learn":[525.3901109],"iteration":832,"passed_time":6.393420246,"remaining_time":1.281754119},
{"learn":[525.2605912],"iteration":833,"passed_time":6.402670191,"remaining_time":1.274392388},
{"learn":[525.1814745],"iteration":834,"passed_time":6.410734383,"remaining_time":1.266791824},
{"learn":[525.0138154],"iteration":835,"passed_time":6.420343024,"remaining_time":1.259493129},
{"learn":[524.9446265],"iteration":836,"passed_time":6.426767728,"remaining_time":1.251568865},
{"learn":[524.84484],"iteration":837,"passed_time":6.43566756,"remaining_time":1.244126664},
{"learn":[524.8198461],"iteration":838,"passed_time":6.441457994,"remaining_time":1.236084311},
{"learn":[524.7118426],"iteration":839,"passed_time":6.449146406,"remaining_time":1.228408839},
{"learn":[524.6291744],"iteration":840,"passed_time":6.456964273,"remaining_time":1.220757811},
{"learn":[524.5456338],"iteration":841,"passed_time":6.465109838,"remaining_time":1.213167879},
{"learn":[524.4669544],"iteration":842,"passed_time":6.473666597,"remaining_time":1.20565321},
{"learn":[524.3765194],"iteration":843,"passed_time":6.480555453,"remaining_time":1.197827785},
{"learn":[524.3437646],"iteration":844,"passed_time":6.48618535,"remaining_time":1.189773644},
{"learn":[524.2770075],"iteration":845,"passed_time":6.494005259,"remaining_time":1.182123889},
{"learn":[524.2031938],"iteration":846,"passed_time":6.501279227,"remaining_time":1.174375114},
{"learn":[523.9931713],"iteration":847,"passed_time":6.514333546,"remaining_time":1.16766356},
{"learn":[523.9271687],"iteration":848,"passed_time":6.521647346,"remaining_time":1.159916077},
{"learn":[523.8902153],"iteration":849,"passed_time":6.528654032,"remaining_time":1.152115417},
{"learn":[523.8544972],"iteration":850,"passed_time":6.535843003,"remaining_time":1.14434854},
{"learn":[523.7481926],"iteration":851,"passed_time":6.544387429,"remaining_time":1.136818474},
{"learn":[523.6539667],"iteration":852,"passed_time":6.553617624,"remaining_time":1.12940421},
{"learn":[523.5296012],"iteration":853,"passed_time":6.56228438,"remaining_time":1.121889367},
{"learn":[523.4918447],"iteration":854,"passed_time":6.568836164,"remaining_time":1.114013151},
{"learn":[523.413233],"iteration":855,"passed_time":6.575985386,"remaining_time":1.106240532},
{"learn":[523.2977377],"iteration":856,"passed_time":6.584739722,"remaining_time":1.0987372},
{"learn":[523.2837802],"iteration":857,"passed_time":6.590530281,"remaining_time":1.090740443},
{"learn":[523.1781955],"iteration":858,"passed_time":6.598824716,"remaining_time":1.083159819},
{"learn":[523.1306314],"iteration":859,"passed_time":6.60546383,"remaining_time":1.075308065},
{"learn":[523.0638299],"iteration":860,"passed_time":6.614093587,"remaining_time":1.067780498},
{"learn":[522.9158236],"iteration":861,"passed_time":6.624844523,"remaining_time":1.060589958},
{"learn":[522.8625247],"iteration":862,"passed_time":6.631732421,"remaining_time":1.052777916},
{"learn":[522.8041244],"iteration":863,"passed_time":6.638978682,"remaining_time":1.045024422},
{"learn":[522.7264177],"iteration":864,"passed_time":6.647048249,"remaining_time":1.037400594},
{"learn":[522.6398637],"iteration":865,"passed_time":6.654930447,"remaining_time":1.029746744},
{"learn":[522.5956015],"iteration":866,"passed_time":6.661601185,"remaining_time":1.021906525},
{"learn":[522.4808341],"iteration":867,"passed_time":6.670917252,"remaining_time":1.014471287},
{"learn":[522.4194847],"iteration":868,"passed_time":6.678483628,"remaining_time":1.006767958},
{"learn":[522.283484],"iteration":869,"passed_time":6.68806102,"remaining_time":0.9993654397},
{"learn":[522.2374172],"iteration":870,"passed_time":6.695380737,"remaining_time":0.9916235534},
{"learn":[522.133807],"iteration":871,"passed_time":6.70502521,"remaining_time":0.984223884},
{"learn":[522.0998163],"iteration":872,"passed_time":6.71182661,"remaining_time":0.9764054748},
{"learn":[522.0499288],"iteration":873,"passed_time":6.719846429,"remaining_time":0.9687650458},
{"learn":[522.0098732],"iteration":874,"passed_time":6.725863064,"remaining_time":0.9608375805},
{"learn":[521.9185975],"iteration":875,"passed_time":6.7336136,"remaining_time":0.9531599159},
{"learn":[521.8701157],"iteration":876,"passed_time":6.740172216,"remaining_time":0.9453149175},
{"learn":[521.759317],"iteration":877,"passed_time":6.750026933,"remaining_time":0.9379308494},
{"learn":[521.6082492],"iteration":878,"passed_time":6.760987238,"remaining_time":0.9306933512},
{"learn":[521.5220938],"iteration":879,"passed_time":6.769433125,"remaining_time":0.9231045171},
{"learn":[521.4594999],"iteration":880,"passed_time":6.7762749,"remaining_time":0.9152970636},
{"learn":[521.3703279],"iteration":881,"passed_time":6.783191796,"remaining_time":0.9075018503},
{"learn":[521.2338964],"iteration":882,"passed_time":6.792410492,"remaining_time":0.9000136212},
{"learn":[521.1954601],"iteration":883,"passed_time":6.800680719,"remaining_time":0.8923970174},
{"learn":[521.1445889],"iteration":884,"passed_time":6.808507377,"remaining_time":0.8847212976},
{"learn":[521.0923158],"iteration":885,"passed_time":6.816145,"remaining_time":0.8770209142},
{"learn":[521.0475116],"iteration":886,"passed_time":6.8239622,"remaining_time":0.8693435498},
{"learn":[520.9365291],"iteration":887,"passed_time":6.832204012,"remaining_time":0.8617194249},
{"learn":[520.862044],"iteration":888,"passed_time":6.840569527,"remaining_time":0.854109356},
{"learn":[520.7531507],"iteration":889,"passed_time":6.849660977,"remaining_time":0.8465873118},
{"learn":[520.6870673],"iteration":890,"passed_time":6.857118648,"remaining_time":0.8388618772},
{"learn":[520.6365138],"iteration":891,"passed_time":6.865223755,"remaining_time":0.8312154322},
{"learn":[520.5473207],"iteration":892,"passed_time":6.874246957,"remaining_time":0.8236779669},
{"learn":[520.4790019],"iteration":893,"passed_time":6.882924796,"remaining_time":0.8160962286},
{"learn":[520.4116711],"iteration":894,"passed_time":6.890707081,"remaining_time":0.8084069759},
{"learn":[520.3452099],"iteration":895,"passed_time":6.897797971,"remaining_time":0.8006372645},
{"learn":[520.3054662],"iteration":896,"passed_time":6.903716651,"remaining_time":0.792734465},
{"learn":[520.2493684],"iteration":897,"passed_time":6.910428138,"remaining_time":0.7849261359},
{"learn":[520.1526093],"iteration":898,"passed_time":6.919082936,"remaining_time":0.7773385723},
{"learn":[520.0879601],"iteration":899,"passed_time":6.927108212,"remaining_time":0.7696786903},
{"learn":[519.9825874],"iteration":900,"passed_time":6.935921588,"remaining_time":0.7621045918},
{"learn":[519.947193],"iteration":901,"passed_time":6.942157507,"remaining_time":0.7542477114},
{"learn":[519.9210709],"iteration":902,"passed_time":6.948737707,"remaining_time":0.7464314037},
{"learn":[519.8783599],"iteration":903,"passed_time":6.954650886,"remaining_time":0.7385469968},
{"learn":[519.8046589],"iteration":904,"passed_time":6.962699912,"remaining_time":0.730891151},
{"learn":[519.7234411],"iteration":905,"passed_time":6.972121643,"remaining_time":0.7233768592},
{"learn":[519.6582786],"iteration":906,"passed_time":6.978574097,"remaining_time":0.7155539041},
{"learn":[519.569353],"iteration":907,"passed_time":6.986222053,"remaining_time":0.7078550978},
{"learn":[519.4256098],"iteration":908,"passed_time":6.995631117,"remaining_time":0.7003327081},
{"learn":[519.3862493],"iteration":909,"passed_time":7.003470233,"remaining_time":0.6926509022},
{"learn":[519.2523177],"iteration":910,"passed_time":7.015499545,"remaining_time":0.6853781114},
{"learn":[519.1537452],"iteration":911,"passed_time":7.024075136,"remaining_time":0.677761636},
{"learn":[519.0546324],"iteration":912,"passed_time":7.033712027,"remaining_time":0.6702441909},
{"learn":[518.9410514],"iteration":913,"passed_time":7.041960546,"remaining_time":0.6625914737},
{"learn":[518.8728048],"iteration":914,"passed_time":7.048279796,"remaining_time":0.6547582324},
{"learn":[518.7748139],"iteration":915,"passed_time":7.056589813,"remaining_time":0.6471108562},
{"learn":[518.7430038],"iteration":916,"passed_time":7.062957186,"remaining_time":0.6392862012},
{"learn":[518.6453844],"iteration":917,"passed_time":7.07234371,"remaining_time":0.6317344054},
{"learn":[518.5375521],"iteration":918,"passed_time":7.080381153,"remaining_time":0.6240597099},
{"learn":[518.4457766],"iteration":919,"passed_time":7.088401055,"remaining_time":0.6163827004},
{"learn":[518.4110082],"iteration":920,"passed_time":7.095708938,"remaining_time":0.608643872},
{"learn":[518.3199336],"iteration":921,"passed_time":7.103661176,"remaining_time":0.6009604899},
{"learn":[518.2631001],"iteration":922,"passed_time":7.111081639,"remaining_time":0.5932321628},
{"learn":[518.2063149],"iteration":923,"passed_time":7.11935745,"remaining_time":0.5855748552},
{"learn":[518.1737459],"iteration":924,"passed_time":7.127481931,"remaining_time":0.5779039404},
{"learn":[518.1076607],"iteration":925,"passed_time":7.135186969,"remaining_time":0.5701985267},
{"learn":[518.0830873],"iteration":926,"passed_time":7.141374306,"remaining_time":0.5623735969},
{"learn":[518.0289345],"iteration":927,"passed_time":7.147775345,"remaining_time":0.5545687767},
{"learn":[517.9663867],"iteration":928,"passed_time":7.155379594,"remaining_time":0.5468589356},
{"learn":[517.9079071],"iteration":929,"passed_time":7.164042349,"remaining_time":0.539228994},
{"learn":[517.796226],"iteration":930,"passed_time":7.172384824,"remaining_time":0.5315730965},
{"learn":[517.7374602],"iteration":931,"passed_time":7.180238731,"remaining_time":0.5238800791},
{"learn":[517.6384709],"iteration":932,"passed_time":7.188775325,"remaining_time":0.5162357414},
{"learn":[517.617515],"iteration":933,"passed_time":7.194837416,"remaining_time":0.5084146354},
{"learn":[517.450958],"iteration":934,"passed_time":7.205162325,"remaining_time":0.5008936376},
{"learn":[517.3650614],"iteration":935,"passed_time":7.213472426,"remaining_time":0.4932288838},
{"learn":[517.245985],"iteration":936,"passed_time":7.222748037,"remaining_time":0.4856276695},
{"learn":[517.1490601],"iteration":937,"passed_time":7.230473115,"remaining_time":0.4779203978},
{"learn":[517.1155842],"iteration":938,"passed_time":7.238348313,"remaining_time":0.4702228404},
{"learn":[517.0280902],"iteration":939,"passed_time":7.246908239,"remaining_time":0.462568611},
{"learn":[516.9816844],"iteration":940,"passed_time":7.255422875,"remaining_time":0.454909617},
{"learn":[516.8913487],"iteration":941,"passed_time":7.264050132,"remaining_time":0.4472557406},
{"learn":[516.8053465],"iteration":942,"passed_time":7.272877174,"remaining_time":0.4396118758},
{"learn":[516.73822],"iteration":943,"passed_time":7.280436382,"remaining_time":0.4318902939},
{"learn":[516.6932506],"iteration":944,"passed_time":7.28838212,"remaining_time":0.424191552},
{"learn":[516.6397128],"iteration":945,"passed_time":7.296252277,"remaining_time":0.4164879735},
{"learn":[516.5985689],"iteration":946,"passed_time":7.303448039,"remaining_time":0.4087463},
{"learn":[516.5055973],"iteration":947,"passed_time":7.311452692,"remaining_time":0.4010501477},
{"learn":[516.4167074],"iteration":948,"passed_time":7.32109029,"remaining_time":0.393441101},
{"learn":[516.3438921],"iteration":949,"passed_time":7.329794336,"remaining_time":0.3857786493},
{"learn":[516.3193041],"iteration":950,"passed_time":7.335908885,"remaining_time":0.377980584},
{"learn":[516.2723033],"iteration":951,"passed_time":7.342786199,"remaining_time":0.3702245142},
{"learn":[516.2115741],"iteration":952,"passed_time":7.3495851,"remaining_time":0.3624664215},
{"learn":[516.1225101],"iteration":953,"passed_time":7.359195741,"remaining_time":0.3548459162},
{"learn":[515.9954795],"iteration":954,"passed_time":7.367574256,"remaining_time":0.3471631848},
{"learn":[515.9363652],"iteration":955,"passed_time":7.375169505,"remaining_time":0.3394429479},
{"learn":[515.8797279],"iteration":956,"passed_time":7.382129442,"remaining_time":0.3316944263},
{"learn":[515.8109924],"iteration":957,"passed_time":7.389861062,"remaining_time":0.3239813827},
{"learn":[515.7043664],"iteration":958,"passed_time":7.398066124,"remaining_time":0.3162885413},
{"learn":[515.6799681],"iteration":959,"passed_time":7.40324687,"remaining_time":0.3084686196},
{"learn":[515.6271607],"iteration":960,"passed_time":7.410889284,"remaining_time":0.3007540917},
{"learn":[515.5910307],"iteration":961,"passed_time":7.416658969,"remaining_time":0.2929657389},
{"learn":[515.5407548],"iteration":962,"passed_time":7.422737143,"remaining_time":0.2851934313},
{"learn":[515.4947393],"iteration":963,"passed_time":7.429065351,"remaining_time":0.2774339758},
{"learn":[515.4053856],"iteration":964,"passed_time":7.437563196,"remaining_time":0.2697561781},
{"learn":[515.3297485],"iteration":965,"passed_time":7.445990251,"remaining_time":0.262074191},
{"learn":[515.2651992],"iteration":966,"passed_time":7.453210012,"remaining_time":0.2543494627},
{"learn":[515.1681859],"iteration":967,"passed_time":7.461772521,"remaining_time":0.246670166},
{"learn":[515.102474],"iteration":968,"passed_time":7.469801173,"remaining_time":0.2389719674},
{"learn":[515.045874],"iteration":969,"passed_time":7.476153255,"remaining_time":0.2312212347},
{"learn":[514.9902068],"iteration":970,"passed_time":7.484499646,"remaining_time":0.2235329451},
{"learn":[514.8790609],"iteration":971,"passed_time":7.494115495,"remaining_time":0.2158798702},
{"learn":[514.8074344],"iteration":972,"passed_time":7.503237194,"remaining_time":0.2082090486},
{"learn":[514.7053456],"iteration":973,"passed_time":7.512248022,"remaining_time":0.2005322881},
{"learn":[514.6700332],"iteration":974,"passed_time":7.518978716,"remaining_time":0.1927943261},
{"learn":[514.585784],"iteration":975,"passed_time":7.527767093,"remaining_time":0.1851090269},
{"learn":[514.5487081],"iteration":976,"passed_time":7.534552869,"remaining_time":0.1773743255},
{"learn":[514.4463614],"iteration":977,"passed_time":7.543282831,"remaining_time":0.1696852989},
{"learn":[514.3472768],"iteration":978,"passed_time":7.552628064,"remaining_time":0.1620073436},
{"learn":[514.3006376],"iteration":979,"passed_time":7.559346842,"remaining_time":0.1542723845},
{"learn":[514.193042],"iteration":980,"passed_time":7.569140102,"remaining_time":0.1465990438},
{"learn":[514.0939873],"iteration":981,"passed_time":7.578035475,"remaining_time":0.1389049272},
{"learn":[514.0242366],"iteration":982,"passed_time":7.586473197,"remaining_time":0.131200452},
{"learn":[513.8999496],"iteration":983,"passed_time":7.596796023,"remaining_time":0.1235251386},
{"learn":[513.8214342],"iteration":984,"passed_time":7.60430465,"remaining_time":0.1158015937},
{"learn":[513.7978291],"iteration":985,"passed_time":7.611876275,"remaining_time":0.1080793792},
{"learn":[513.7475096],"iteration":986,"passed_time":7.619500898,"remaining_time":0.1003581679},
{"learn":[513.7093332],"iteration":987,"passed_time":7.62696311,"remaining_time":0.09263517948},
{"learn":[513.6624984],"iteration":988,"passed_time":7.633682055,"remaining_time":0.08490445157},
{"learn":[513.5670827],"iteration":989,"passed_time":7.642863919,"remaining_time":0.07720064564},
{"learn":[513.4969516],"iteration":990,"passed_time":7.6510049,"remaining_time":0.06948440373},
{"learn":[513.3729592],"iteration":991,"passed_time":7.659536035,"remaining_time":0.06177045189},
{"learn":[513.3450145],"iteration":992,"passed_time":7.664494913,"remaining_time":0.0540296721},
{"learn":[513.2951937],"iteration":993,"passed_time":7.670694417,"remaining_time":0.04630197837},
{"learn":[513.1872648],"iteration":994,"passed_time":7.679235385,"remaining_time":0.03858912254},
{"learn":[513.1030996],"iteration":995,"passed_time":7.688296169,"remaining_time":0.03087669144},
{"learn":[513.069861],"iteration":996,"passed_time":7.694407509,"remaining_time":0.02315268057},
{"learn":[512.9250889],"iteration":997,"passed_time":7.705634597,"remaining_time":0.0154421535},
{"learn":[512.9033405],"iteration":998,"passed_time":7.711485737,"remaining_time":0.007719204942},
{"learn":[512.8327606],"iteration":999,"passed_time":7.718878409,"remaining_time":0}
]}